<root>
   <MetNet>iJR904</MetNet>
   <Method>CBO</Method>
   <Soltype>Optimal</Soltype>
   <Strategy>RPI</Strategy>
   <Time>1.4849414825439453</Time>
   <Vij>0.0</Vij>
   <Vij>0.0</Vij>
   <Vij>0.0</Vij>
   <Vij>0.0</Vij>
   <Vij>0.0</Vij>
   <Vij>0.0</Vij>
   <Vij>0.0</Vij>
   <Vij>0.0</Vij>
   <Vij>0.0</Vij>
   <Vij>0.0</Vij>
   <Vij>0.0</Vij>
   <Vij>0.0</Vij>
   <Vij>0.0</Vij>
   <Vij>0.0</Vij>
   <Vij>0.0</Vij>
   <Vij>0.0</Vij>
   <Vij>0.0</Vij>
   <Vij>0.0</Vij>
   <Vij>0.0</Vij>
   <Vij>0.0</Vij>
   <Vij>0.0</Vij>
   <Vij>0.0</Vij>
   <Vij>0.0</Vij>
   <Vij>0.0</Vij>
   <Vij>0.0</Vij>
   <Vij>0.0</Vij>
   <Vij>0.0</Vij>
   <Vij>0.04892310443372968</Vij>
   <Vij>0.0</Vij>
   <Vij>0.04892310443372968</Vij>
   <Vij>0.0</Vij>
   <Vij>0.0</Vij>
   <Vij>0.0</Vij>
   <Vij>2.089910764945671</Vij>
   <Vij>0.0</Vij>
   <Vij>0.0</Vij>
   <Vij>0.0</Vij>
   <Vij>0.0</Vij>
   <Vij>0.0</Vij>
   <Vij>0.29263264318693866</Vij>
   <Vij>0.29263264318693866</Vij>
   <Vij>0.25005142266128505</Vij>
   <Vij>0.0</Vij>
   <Vij>0.21103295020293444</Vij>
   <Vij>0.7520196878362452</Vij>
   <Vij>0.0</Vij>
   <Vij>0.0</Vij>
   <Vij>0.0</Vij>
   <Vij>9.059834154394386e-06</Vij>
   <Vij>0.0</Vij>
   <Vij>0.0</Vij>
   <Vij>0.0</Vij>
   <Vij>0.0</Vij>
   <Vij>0.0</Vij>
   <Vij>0.0</Vij>
   <Vij>0.0</Vij>
   <Vij>0.0</Vij>
   <Vij>0.0</Vij>
   <Vij>0.29109247133601457</Vij>
   <Vij>0.29263264318693866</Vij>
   <Vij>0.0</Vij>
   <Vij>0.0</Vij>
   <Vij>3.5619802833534777</Vij>
   <Vij>-0.29263264313340187</Vij>
   <Vij>0.0</Vij>
   <Vij>0.0</Vij>
   <Vij>0.0380513034760952</Vij>
   <Vij>0.0</Vij>
   <Vij>0.0</Vij>
   <Vij>0.0</Vij>
   <Vij>-0.3079678032081574</Vij>
   <Vij>0.0</Vij>
   <Vij>0.045299170771971965</Vij>
   <Vij>0.045299170771971965</Vij>
   <Vij>0.0</Vij>
   <Vij>0.0</Vij>
   <Vij>0.0</Vij>
   <Vij>0.0</Vij>
   <Vij>0.0</Vij>
   <Vij>0.0</Vij>
   <Vij>0.0</Vij>
   <Vij>0.0</Vij>
   <Vij>0.0</Vij>
   <Vij>999999.0</Vij>
   <Vij>-999996.9076349263</Vij>
   <Vij>0.0</Vij>
   <Vij>0.0</Vij>
   <Vij>0.006341883912682533</Vij>
   <Vij>0.254581339773722</Vij>
   <Vij>0.0</Vij>
   <Vij>0.25458133973848224</Vij>
   <Vij>0.00634188390807607</Vij>
   <Vij>999999.0</Vij>
   <Vij>0.03805130344845641</Vij>
   <Vij>0.0</Vij>
   <Vij>-999999.0</Vij>
   <Vij>0.0</Vij>
   <Vij>-0.7337849597679451</Vij>
   <Vij>0.0</Vij>
   <Vij>0.0</Vij>
   <Vij>0.0</Vij>
   <Vij>0.2111475888189003</Vij>
   <Vij>0.2622812927002087</Vij>
   <Vij>0.4329776279628277</Vij>
   <Vij>0.26228129266988964</Vij>
   <Vij>0.0</Vij>
   <Vij>0.012518878834542162</Vij>
   <Vij>0.012271545362127195</Vij>
   <Vij>0.08835512660731579</Vij>
   <Vij>0.017180163506978072</Vij>
   <Vij>0.12271545362127194</Vij>
   <Vij>0.0</Vij>
   <Vij>0.022830782069073848</Vij>
   <Vij>0.0</Vij>
   <Vij>0.0</Vij>
   <Vij>-0.29263264313340187</Vij>
   <Vij>0.20747020213563142</Vij>
   <Vij>0.0</Vij>
   <Vij>0.0</Vij>
   <Vij>0.0</Vij>
   <Vij>0.0</Vij>
   <Vij>0.0</Vij>
   <Vij>0.0</Vij>
   <Vij>5.345302151115635e-05</Vij>
   <Vij>0.0</Vij>
   <Vij>0.0</Vij>
   <Vij>0.5145161353284493</Vij>
   <Vij>0.43297762797283434</Vij>
   <Vij>-0.4329776279628277</Vij>
   <Vij>0.15817884781277458</Vij>
   <Vij>0.2854753742049671</Vij>
   <Vij>0.0</Vij>
   <Vij>0.025005142320878804</Vij>
   <Vij>0.050010284525342286</Vij>
   <Vij>0.0</Vij>
   <Vij>0.0</Vij>
   <Vij>0.5400567139434493</Vij>
   <Vij>0.0</Vij>
   <Vij>0.0</Vij>
   <Vij>0.0</Vij>
   <Vij>-999999.0</Vij>
   <Vij>0.0</Vij>
   <Vij>0.7337849597679451</Vij>
   <Vij>0.0</Vij>
   <Vij>0.2781369085399076</Vij>
   <Vij>0.13793597498442978</Vij>
   <Vij>0.002473334724147902</Vij>
   <Vij>0.3723591837456093</Vij>
   <Vij>0.0</Vij>
   <Vij>0.0</Vij>
   <Vij>0.0</Vij>
   <Vij>0.0</Vij>
   <Vij>0.0</Vij>
   <Vij>0.0</Vij>
   <Vij>1.8119668308788772e-05</Vij>
   <Vij>0.00584359304048121</Vij>
   <Vij>0.0</Vij>
   <Vij>0.0</Vij>
   <Vij>0.0</Vij>
   <Vij>-21.82296592288185</Vij>
   <Vij>5.378772639556926</Vij>
   <Vij>0.0</Vij>
   <Vij>0.0</Vij>
   <Vij>-7.765340425889008</Vij>
   <Vij>0.0</Vij>
   <Vij>0.0</Vij>
   <Vij>0.0</Vij>
   <Vij>0.0</Vij>
   <Vij>0.0</Vij>
   <Vij>0.0</Vij>
   <Vij>0.0</Vij>
   <Vij>0.0</Vij>
   <Vij>0.0</Vij>
   <Vij>0.0</Vij>
   <Vij>3.5619802833371303</Vij>
   <Vij>0.0</Vij>
   <Vij>0.0</Vij>
   <Vij>0.3723591837456093</Vij>
   <Vij>0.0</Vij>
   <Vij>-0.18723778042476624</Vij>
   <Vij>0.0</Vij>
   <Vij>0.0</Vij>
   <Vij>0.7520196878362452</Vij>
   <Vij>0.25005142266128505</Vij>
   <Vij>0.13716588909753102</Vij>
   <Vij>0.0</Vij>
   <Vij>0.0</Vij>
   <Vij>1.5456923516251433</Vij>
   <Vij>0.0</Vij>
   <Vij>0.0</Vij>
   <Vij>0.0</Vij>
   <Vij>0.0</Vij>
   <Vij>0.0</Vij>
   <Vij>0.0</Vij>
   <Vij>0.2111475888189003</Vij>
   <Vij>0.132273578654158</Vij>
   <Vij>0.0</Vij>
   <Vij>0.0</Vij>
   <Vij>0.0</Vij>
   <Vij>0.32035573569938547</Vij>
   <Vij>0.0</Vij>
   <Vij>0.0</Vij>
   <Vij>0.0</Vij>
   <Vij>40.0</Vij>
   <Vij>0.0</Vij>
   <Vij>0.0</Vij>
   <Vij>999999.0</Vij>
   <Vij>0.32035573569938547</Vij>
   <Vij>0.06767696118913591</Vij>
   <Vij>0.045299170771971965</Vij>
   <Vij>0.0</Vij>
   <Vij>7.6</Vij>
   <Vij>0.045299170771971965</Vij>
   <Vij>0.2854753742049671</Vij>
   <Vij>-999999.0</Vij>
   <Vij>0.16082021011970937</Vij>
   <Vij>0.0</Vij>
   <Vij>0.0</Vij>
   <Vij>-0.28547537419945</Vij>
   <Vij>0.08153850738954946</Vij>
   <Vij>0.0</Vij>
   <Vij>0.0</Vij>
   <Vij>55.169487166800536</Vij>
   <Vij>0.0</Vij>
   <Vij>0.0</Vij>
   <Vij>9.059834154394386e-06</Vij>
   <Vij>0.045299170771971965</Vij>
   <Vij>0.0</Vij>
   <Vij>0.0</Vij>
   <Vij>0.37235918373335153</Vij>
   <Vij>0.0</Vij>
   <Vij>0.0</Vij>
   <Vij>0.015220521379382566</Vij>
   <Vij>0.0</Vij>
   <Vij>0.3723591837456093</Vij>
   <Vij>0.0</Vij>
   <Vij>0.295350593433257</Vij>
   <Vij>0.0</Vij>
   <Vij>0.32035573571920395</Vij>
   <Vij>0.0</Vij>
   <Vij>0.0</Vij>
   <Vij>0.0</Vij>
   <Vij>0.0</Vij>
   <Vij>0.00634188390807607</Vij>
   <Vij>0.2111475888189003</Vij>
   <Vij>0.0</Vij>
   <Vij>0.0</Vij>
   <Vij>0.0</Vij>
   <Vij>0.0</Vij>
   <Vij>0.0</Vij>
   <Vij>0.007610260689691283</Vij>
   <Vij>0.0</Vij>
   <Vij>0.0</Vij>
   <Vij>0.0</Vij>
   <Vij>0.007610260689691283</Vij>
   <Vij>0.0</Vij>
   <Vij>0.0</Vij>
   <Vij>0.0</Vij>
   <Vij>0.0</Vij>
   <Vij>0.0</Vij>
   <Vij>12.353467164793983</Vij>
   <Vij>0.045299170771971965</Vij>
   <Vij>0.0</Vij>
   <Vij>0.045299170771971965</Vij>
   <Vij>0.0</Vij>
   <Vij>0.0</Vij>
   <Vij>0.0</Vij>
   <Vij>5.345302151115635e-05</Vij>
   <Vij>0.9059834154394385</Vij>
   <Vij>5.345302151115635e-05</Vij>
   <Vij>0.0</Vij>
   <Vij>0.0</Vij>
   <Vij>0.1872377803856261</Vij>
   <Vij>40.98978345131036</Vij>
   <Vij>0.0</Vij>
   <Vij>0.022377790417522192</Vij>
   <Vij>0.0</Vij>
   <Vij>0.0</Vij>
   <Vij>0.0</Vij>
   <Vij>0.0</Vij>
   <Vij>0.0</Vij>
   <Vij>0.0</Vij>
   <Vij>0.0</Vij>
   <Vij>0.0</Vij>
   <Vij>0.0</Vij>
   <Vij>0.0</Vij>
   <Vij>0.0</Vij>
   <Vij>0.0</Vij>
   <Vij>0.3079678031957674</Vij>
   <Vij>0.0</Vij>
   <Vij>0.0</Vij>
   <Vij>0.0</Vij>
   <Vij>8.614947858732194</Vij>
   <Vij>0.0</Vij>
   <Vij>0.0</Vij>
   <Vij>0.0</Vij>
   <Vij>0.0</Vij>
   <Vij>0.0</Vij>
   <Vij>0.0</Vij>
   <Vij>0.0</Vij>
   <Vij>0.0</Vij>
   <Vij>0.0</Vij>
   <Vij>0.0</Vij>
   <Vij>0.0</Vij>
   <Vij>0.0</Vij>
   <Vij>0.0</Vij>
   <Vij>0.0</Vij>
   <Vij>0.0</Vij>
   <Vij>0.0</Vij>
   <Vij>0.0</Vij>
   <Vij>0.0</Vij>
   <Vij>0.0</Vij>
   <Vij>0.0</Vij>
   <Vij>0.0</Vij>
   <Vij>0.0</Vij>
   <Vij>0.0</Vij>
   <Vij>0.0</Vij>
   <Vij>0.0</Vij>
   <Vij>0.0</Vij>
   <Vij>0.0</Vij>
   <Vij>0.0</Vij>
   <Vij>0.0</Vij>
   <Vij>0.0</Vij>
   <Vij>0.0</Vij>
   <Vij>0.0</Vij>
   <Vij>0.0</Vij>
   <Vij>0.0</Vij>
   <Vij>0.0</Vij>
   <Vij>0.0</Vij>
   <Vij>0.0</Vij>
   <Vij>21.82296592288185</Vij>
   <Vij>0.0</Vij>
   <Vij>0.0</Vij>
   <Vij>0.051668234182511215</Vij>
   <Vij>9.059834154394386e-06</Vij>
   <Vij>0.0</Vij>
   <Vij>0.0</Vij>
   <Vij>0.0</Vij>
   <Vij>0.0</Vij>
   <Vij>0.0</Vij>
   <Vij>0.0</Vij>
   <Vij>0.0</Vij>
   <Vij>0.0</Vij>
   <Vij>0.0</Vij>
   <Vij>0.0</Vij>
   <Vij>0.0</Vij>
   <Vij>0.09696740495448318</Vij>
   <Vij>0.0</Vij>
   <Vij>0.0</Vij>
   <Vij>0.0</Vij>
   <Vij>0.0</Vij>
   <Vij>0.0</Vij>
   <Vij>0.0</Vij>
   <Vij>0.0</Vij>
   <Vij>0.0</Vij>
   <Vij>0.0</Vij>
   <Vij>0.0</Vij>
   <Vij>0.0</Vij>
   <Vij>8.884405284188688</Vij>
   <Vij>0.0</Vij>
   <Vij>0.0</Vij>
   <Vij>0.0</Vij>
   <Vij>0.0</Vij>
   <Vij>0.0</Vij>
   <Vij>0.0</Vij>
   <Vij>0.0</Vij>
   <Vij>0.0</Vij>
   <Vij>0.06523080591163957</Vij>
   <Vij>0.0</Vij>
   <Vij>0.0</Vij>
   <Vij>0.0</Vij>
   <Vij>0.0</Vij>
   <Vij>0.0</Vij>
   <Vij>0.0</Vij>
   <Vij>0.0</Vij>
   <Vij>0.0</Vij>
   <Vij>0.0</Vij>
   <Vij>0.0</Vij>
   <Vij>-0.14957786188460886</Vij>
   <Vij>0.0</Vij>
   <Vij>0.0</Vij>
   <Vij>0.0</Vij>
   <Vij>0.0</Vij>
   <Vij>0.0</Vij>
   <Vij>0.0</Vij>
   <Vij>0.0</Vij>
   <Vij>0.19025651724228207</Vij>
   <Vij>0.19025651724228207</Vij>
   <Vij>0.0</Vij>
   <Vij>0.0</Vij>
   <Vij>0.0</Vij>
   <Vij>0.0</Vij>
   <Vij>0.0</Vij>
   <Vij>9.842540082405321</Vij>
   <Vij>0.0</Vij>
   <Vij>0.0</Vij>
   <Vij>0.0</Vij>
   <Vij>-10.0</Vij>
   <Vij>0.0</Vij>
   <Vij>0.0</Vij>
   <Vij>0.0</Vij>
   <Vij>0.0</Vij>
   <Vij>0.0</Vij>
   <Vij>0.0</Vij>
   <Vij>0.0</Vij>
   <Vij>0.0</Vij>
   <Vij>0.0</Vij>
   <Vij>0.0</Vij>
   <Vij>0.0</Vij>
   <Vij>0.0</Vij>
   <Vij>0.0</Vij>
   <Vij>0.0</Vij>
   <Vij>0.0</Vij>
   <Vij>0.0</Vij>
   <Vij>0.0</Vij>
   <Vij>0.0</Vij>
   <Vij>0.0</Vij>
   <Vij>-999998.9820615284</Vij>
   <Vij>0.0</Vij>
   <Vij>999999.0</Vij>
   <Vij>0.0</Vij>
   <Vij>0.0</Vij>
   <Vij>0.0</Vij>
   <Vij>0.0</Vij>
   <Vij>0.0</Vij>
   <Vij>0.0</Vij>
   <Vij>0.0</Vij>
   <Vij>14.003069083672017</Vij>
   <Vij>0.4329776279628277</Vij>
   <Vij>0.0</Vij>
   <Vij>0.0</Vij>
   <Vij>0.045299170771971965</Vij>
   <Vij>0.0</Vij>
   <Vij>0.0</Vij>
   <Vij>0.13952144597767352</Vij>
   <Vij>0.0</Vij>
   <Vij>0.0</Vij>
   <Vij>0.06523080591163957</Vij>
   <Vij>1.1474977561442135</Vij>
   <Vij>0.43947262305300683</Vij>
   <Vij>10.0</Vij>
   <Vij>0.0</Vij>
   <Vij>0.0</Vij>
   <Vij>0.0</Vij>
   <Vij>0.0</Vij>
   <Vij>0.0</Vij>
   <Vij>0.13952144597767352</Vij>
   <Vij>1.722843430102444</Vij>
   <Vij>0.0</Vij>
   <Vij>0.0</Vij>
   <Vij>0.0</Vij>
   <Vij>0.0</Vij>
   <Vij>0.0</Vij>
   <Vij>0.0</Vij>
   <Vij>0.19025651724228207</Vij>
   <Vij>0.0</Vij>
   <Vij>0.0</Vij>
   <Vij>0.0</Vij>
   <Vij>0.0</Vij>
   <Vij>0.0</Vij>
   <Vij>0.0</Vij>
   <Vij>-12.919286195654422</Vij>
   <Vij>0.0</Vij>
   <Vij>0.43297762797283434</Vij>
   <Vij>0.0</Vij>
   <Vij>0.0</Vij>
   <Vij>0.0</Vij>
   <Vij>0.0</Vij>
   <Vij>-0.025005142320878804</Vij>
   <Vij>0.0</Vij>
   <Vij>0.0</Vij>
   <Vij>0.0</Vij>
   <Vij>0.0</Vij>
   <Vij>0.0</Vij>
   <Vij>0.0</Vij>
   <Vij>0.0</Vij>
   <Vij>-40.98978345131036</Vij>
   <Vij>-9.679946280317381</Vij>
   <Vij>0.0</Vij>
   <Vij>0.0</Vij>
   <Vij>0.0</Vij>
   <Vij>0.0</Vij>
   <Vij>0.0</Vij>
   <Vij>0.0</Vij>
   <Vij>0.0</Vij>
   <Vij>2.5228883929084986</Vij>
   <Vij>0.0</Vij>
   <Vij>0.0</Vij>
   <Vij>0.0</Vij>
   <Vij>0.0</Vij>
   <Vij>0.0</Vij>
   <Vij>0.0</Vij>
   <Vij>0.0</Vij>
   <Vij>0.0</Vij>
   <Vij>0.0</Vij>
   <Vij>0.0</Vij>
   <Vij>0.0</Vij>
   <Vij>0.0</Vij>
   <Vij>0.0</Vij>
   <Vij>-20.0</Vij>
   <Vij>0.0</Vij>
   <Vij>0.0</Vij>
   <Vij>0.08153850738954946</Vij>
   <Vij>0.08153850738954946</Vij>
   <Vij>0.0</Vij>
   <Vij>0.0</Vij>
   <Vij>0.0</Vij>
   <Vij>0.0</Vij>
   <Vij>0.0</Vij>
   <Vij>0.0</Vij>
   <Vij>0.0</Vij>
   <Vij>0.0</Vij>
   <Vij>0.0</Vij>
   <Vij>0.045299170771971965</Vij>
   <Vij>0.0</Vij>
   <Vij>0.0</Vij>
   <Vij>0.0</Vij>
   <Vij>0.0</Vij>
   <Vij>0.005843593029584378</Vij>
   <Vij>0.0</Vij>
   <Vij>-0.8259280024794862</Vij>
   <Vij>0.0</Vij>
   <Vij>0.0</Vij>
   <Vij>0.0</Vij>
   <Vij>0.045299170771971965</Vij>
   <Vij>0.0</Vij>
   <Vij>0.0</Vij>
   <Vij>0.0</Vij>
   <Vij>0.022830782069073848</Vij>
   <Vij>0.022830782069073848</Vij>
   <Vij>0.022830782069073848</Vij>
   <Vij>0.0</Vij>
   <Vij>0.0</Vij>
   <Vij>0.0</Vij>
   <Vij>0.25223484269249413</Vij>
   <Vij>0.0</Vij>
   <Vij>0.0</Vij>
   <Vij>-0.41342922404874116</Vij>
   <Vij>0.2811556453965635</Vij>
   <Vij>0.132273578654158</Vij>
   <Vij>9.842540082396626</Vij>
   <Vij>0.0</Vij>
   <Vij>0.0</Vij>
   <Vij>0.0</Vij>
   <Vij>0.0</Vij>
   <Vij>0.08153850738954946</Vij>
   <Vij>0.0</Vij>
   <Vij>0.0</Vij>
   <Vij>0.0</Vij>
   <Vij>0.0</Vij>
   <Vij>0.0</Vij>
   <Vij>0.0</Vij>
   <Vij>0.0</Vij>
   <Vij>0.0</Vij>
   <Vij>0.051668234182511215</Vij>
   <Vij>0.0</Vij>
   <Vij>0.0</Vij>
   <Vij>0.0</Vij>
   <Vij>0.1872377803856261</Vij>
   <Vij>0.0</Vij>
   <Vij>0.0</Vij>
   <Vij>0.0</Vij>
   <Vij>1.1643640289548784</Vij>
   <Vij>0.0</Vij>
   <Vij>0.0</Vij>
   <Vij>2.3976162543373145</Vij>
   <Vij>0.0</Vij>
   <Vij>0.0</Vij>
   <Vij>0.0</Vij>
   <Vij>0.0</Vij>
   <Vij>0.0</Vij>
   <Vij>0.0</Vij>
   <Vij>0.08153850738954946</Vij>
   <Vij>0.0</Vij>
   <Vij>0.045299170771971965</Vij>
   <Vij>0.08153850738954946</Vij>
   <Vij>0.0</Vij>
   <Vij>0.04892310443372968</Vij>
   <Vij>9.059834154394386e-06</Vij>
   <Vij>-0.25005142262671143</Vij>
   <Vij>0.0</Vij>
   <Vij>0.0</Vij>
   <Vij>0.0</Vij>
   <Vij>0.0</Vij>
   <Vij>-0.5145161353284493</Vij>
   <Vij>0.25005142266128505</Vij>
   <Vij>0.0</Vij>
   <Vij>0.2910924713806916</Vij>
   <Vij>0.0</Vij>
   <Vij>0.25223484269249413</Vij>
   <Vij>0.0</Vij>
   <Vij>0.0</Vij>
   <Vij>0.030441042758765132</Vij>
   <Vij>0.0</Vij>
   <Vij>0.03805130344845641</Vij>
   <Vij>0.03805130344845641</Vij>
   <Vij>0.03805130344845641</Vij>
   <Vij>0.0</Vij>
   <Vij>0.0</Vij>
   <Vij>999999.0</Vij>
   <Vij>-999999.0</Vij>
   <Vij>0.0</Vij>
   <Vij>0.0</Vij>
   <Vij>0.38776090180807965</Vij>
   <Vij>0.0</Vij>
   <Vij>-0.38776090182363987</Vij>
   <Vij>-0.38776090182363987</Vij>
   <Vij>0.38776090180807965</Vij>
   <Vij>0.0</Vij>
   <Vij>0.0</Vij>
   <Vij>0.0</Vij>
   <Vij>-0.752019687788561</Vij>
   <Vij>-0.21114758879411966</Vij>
   <Vij>0.0</Vij>
   <Vij>0.0</Vij>
   <Vij>0.0</Vij>
   <Vij>0.0</Vij>
   <Vij>0.0</Vij>
   <Vij>0.0</Vij>
   <Vij>0.0</Vij>
   <Vij>0.0</Vij>
   <Vij>0.0</Vij>
   <Vij>0.38776090180807965</Vij>
   <Vij>0.0</Vij>
   <Vij>0.00634188390807607</Vij>
   <Vij>0.0</Vij>
   <Vij>0.0</Vij>
   <Vij>0.0</Vij>
   <Vij>0.132273578654158</Vij>
   <Vij>0.0</Vij>
   <Vij>0.0</Vij>
   <Vij>0.007610260689691283</Vij>
   <Vij>0.0</Vij>
   <Vij>0.0</Vij>
   <Vij>0.0</Vij>
   <Vij>0.0</Vij>
   <Vij>0.0</Vij>
   <Vij>0.0</Vij>
   <Vij>0.0</Vij>
   <Vij>0.0</Vij>
   <Vij>0.0</Vij>
   <Vij>0.0</Vij>
   <Vij>0.0</Vij>
   <Vij>0.0</Vij>
   <Vij>0.0</Vij>
   <Vij>0.007610260689691283</Vij>
   <Vij>0.0</Vij>
   <Vij>0.0</Vij>
   <Vij>0.0</Vij>
   <Vij>0.0</Vij>
   <Vij>0.0</Vij>
   <Vij>0.0</Vij>
   <Vij>0.0</Vij>
   <Vij>0.0</Vij>
   <Vij>0.0</Vij>
   <Vij>0.0</Vij>
   <Vij>0.0</Vij>
   <Vij>0.0</Vij>
   <Vij>0.0</Vij>
   <Vij>0.0</Vij>
   <Vij>0.0</Vij>
   <Vij>0.0</Vij>
   <Vij>0.0</Vij>
   <Vij>0.0</Vij>
   <Vij>0.0</Vij>
   <Vij>0.0</Vij>
   <Vij>0.0</Vij>
   <Vij>2.4429154251092866</Vij>
   <Vij>0.0</Vij>
   <Vij>0.0</Vij>
   <Vij>0.0</Vij>
   <Vij>0.007610260689691283</Vij>
   <Vij>0.007610260689691283</Vij>
   <Vij>0.0</Vij>
   <Vij>0.0</Vij>
   <Vij>5.345302151115635e-05</Vij>
   <Vij>0.0</Vij>
   <Vij>0.0</Vij>
   <Vij>0.0</Vij>
   <Vij>0.0</Vij>
   <Vij>0.00634188390807607</Vij>
   <Vij>0.947493763291277</Vij>
   <Vij>0.0</Vij>
   <Vij>0.0</Vij>
   <Vij>0.0</Vij>
   <Vij>0.947493763291277</Vij>
   <Vij>0.0</Vij>
   <Vij>0.17757274942612997</Vij>
   <Vij>0.006341883912682533</Vij>
   <Vij>0.00634188390807607</Vij>
   <Vij>0.0</Vij>
   <Vij>0.0</Vij>
   <Vij>0.0</Vij>
   <Vij>0.0</Vij>
   <Vij>0.0</Vij>
   <Vij>0.0</Vij>
   <Vij>0.0</Vij>
   <Vij>0.0</Vij>
   <Vij>0.0</Vij>
   <Vij>0.0</Vij>
   <Vij>0.0</Vij>
   <Vij>0.0</Vij>
   <Vij>0.0</Vij>
   <Vij>0.0</Vij>
   <Vij>0.0</Vij>
   <Vij>0.0</Vij>
   <Vij>2.089910764945671</Vij>
   <Vij>11.327320709242485</Vij>
   <Vij>37.059291501916555</Vij>
   <Vij>0.0</Vij>
   <Vij>0.0</Vij>
   <Vij>0.0</Vij>
   <Vij>0.0</Vij>
   <Vij>0.0</Vij>
   <Vij>0.0004801712101840364</Vij>
   <Vij>0.0</Vij>
   <Vij>0.00634188390807607</Vij>
   <Vij>0.0</Vij>
   <Vij>0.0</Vij>
   <Vij>0.0</Vij>
   <Vij>0.0</Vij>
   <Vij>0.0</Vij>
   <Vij>0.002473334724147902</Vij>
   <Vij>0.0</Vij>
   <Vij>0.0</Vij>
   <Vij>0.0</Vij>
   <Vij>0.0</Vij>
   <Vij>999999.0</Vij>
   <Vij>0.0</Vij>
   <Vij>0.0</Vij>
   <Vij>0.0</Vij>
   <Vij>-999995.9947334216</Vij>
   <Vij>0.36592670145910233</Vij>
   <Vij>0.0</Vij>
   <Vij>0.0</Vij>
   <Vij>0.1530287527712062</Vij>
   <Vij>0.0</Vij>
   <Vij>0.022377790417522192</Vij>
   <Vij>-0.18723778042476624</Vij>
   <Vij>0.0</Vij>
   <Vij>0.002473334724147902</Vij>
   <Vij>0.0</Vij>
   <Vij>0.0</Vij>
   <Vij>0.0</Vij>
   <Vij>-0.022377790417522192</Vij>
   <Vij>0.023011978715658188</Vij>
   <Vij>0.0</Vij>
   <Vij>0.0</Vij>
   <Vij>1.5456923516467214</Vij>
   <Vij>0.0</Vij>
   <Vij>9.679946280317381</Vij>
   <Vij>0.0</Vij>
   <Vij>0.0</Vij>
   <Vij>0.0</Vij>
   <Vij>0.0</Vij>
   <Vij>0.0</Vij>
   <Vij>0.0</Vij>
   <Vij>0.0</Vij>
   <Vij>0.0</Vij>
   <Vij>0.0</Vij>
   <Vij>0.0</Vij>
   <Vij>0.0</Vij>
   <Vij>0.0</Vij>
   <Vij>0.0</Vij>
   <Vij>0.002473334724147902</Vij>
   <Vij>0.0</Vij>
   <Vij>0.0</Vij>
   <Vij>0.0</Vij>
   <Vij>0.0</Vij>
   <Vij>0.0</Vij>
   <Vij>0.0</Vij>
   <Vij>-0.0652308058924973</Vij>
   <Vij>0.0</Vij>
   <Vij>1.6496019188314894</Vij>
   <Vij>0.0</Vij>
   <Vij>0.1872377803856261</Vij>
   <Vij>4.074184769298881</Vij>
   <Vij>0.0</Vij>
   <Vij>0.0</Vij>
   <Vij>-0.0</Vij>
   <Vij>0.0</Vij>
   <Vij>-14.003069083672017</Vij>
   <Vij>9.842540082396626</Vij>
   <Vij>0.0</Vij>
   <Vij>-12.353467164793983</Vij>
   <Vij>-0.1574599175946787</Vij>
   <Vij>0.0</Vij>
   <Vij>0.0</Vij>
   <Vij>0.0</Vij>
   <Vij>0.0</Vij>
   <Vij>0.0</Vij>
   <Vij>0.0</Vij>
   <Vij>0.0</Vij>
   <Vij>0.0</Vij>
   <Vij>0.03270600129736373</Vij>
   <Vij>0.03270600130781531</Vij>
   <Vij>0.0</Vij>
   <Vij>-0.18723778042476624</Vij>
   <Vij>0.0</Vij>
   <Vij>-0.159453081083484</Vij>
   <Vij>0.18723778042476624</Vij>
   <Vij>0.0</Vij>
   <Vij>20.0</Vij>
   <Vij>0.0</Vij>
   <Vij>0.0</Vij>
   <Vij>0.254581339773722</Vij>
   <Vij>0.0</Vij>
   <Vij>0.0</Vij>
   <Vij>0.8259280024794862</Vij>
   <Vij>0.0</Vij>
   <Vij>0.0</Vij>
   <Vij>0.0</Vij>
   <Vij>0.0</Vij>
   <Vij>0.0</Vij>
   <Vij>0.0</Vij>
   <Vij>0.0</Vij>
   <Vij>0.0</Vij>
   <Vij>0.0</Vij>
   <Vij>0.0</Vij>
   <Vij>9.059834154394386e-06</Vij>
   <Vij>0.0</Vij>
   <Vij>0.0</Vij>
   <Vij>5.345302151115635e-05</Vij>
   <Vij>0.0</Vij>
   <Vij>0.38776090180807965</Vij>
   <Vij>0.0</Vij>
   <Vij>0.0</Vij>
   <Vij>0.0</Vij>
   <Vij>0.0</Vij>
   <Vij>0.2854753742049671</Vij>
   <Vij>0.0</Vij>
   <Vij>0.0</Vij>
   <Vij>3.043483677203767</Vij>
   <Vij>0.0</Vij>
   <Vij>0.0</Vij>
   <Vij>0.0</Vij>
   <Vij>0.0</Vij>
   <Vij>0.03805130344845642</Vij>
   <Vij>0.0</Vij>
   <Vij>0.0</Vij>
   <Vij>0.0</Vij>
   <Vij>5.345302151115635e-05</Vij>
   <Vij>0.0</Vij>
   <Vij>0.0</Vij>
   <Vij>0.0</Vij>
   <Vij>-0.19357966433744878</Vij>
   <Vij>-0.28547537419945</Vij>
   <Vij>0.0</Vij>
   <Vij>0.0</Vij>
   <Vij>0.18723778042476624</Vij>
   <Vij>5.345302151115635e-05</Vij>
   <Vij>0.0</Vij>
   <Vij>0.0</Vij>
   <Vij>0.19025651724228207</Vij>
   <Vij>0.0</Vij>
   <Vij>0.11868382742256645</Vij>
   <Vij>0.15945308111734116</Vij>
   <Vij>0.0</Vij>
   <Vij>5.345302151115635e-05</Vij>
   <Vij>0.0</Vij>
   <Vij>0.0</Vij>
   <Vij>0.025005142266128502</Vij>
   <Vij>0.0</Vij>
   <Vij>0.0</Vij>
   <Vij>0.0</Vij>
   <Vij>0.2111475888189003</Vij>
   <Vij>0.025005142266128502</Vij>
   <Vij>0.0</Vij>
   <Vij>0.4329776279628277</Vij>
   <Vij>0.43297762797283434</Vij>
   <Vij>0.04892310443372968</Vij>
   <Vij>0.08153850738954946</Vij>
   <Vij>0.12271545362127194</Vij>
   <Vij>9.131683233485282</Vij>
   <Vij>0.0</Vij>
   <Vij>0.0</Vij>
   <Vij>0.0</Vij>
   <Vij>0.4329776279628277</Vij>
   <Vij>0.08153850738954946</Vij>
   <Vij>0.43297762797283434</Vij>
   <Vij>0.0</Vij>
   <Vij>0.002473334724147902</Vij>
   <Vij>0.015220521367155015</Vij>
   <Vij>0.08153850738954946</Vij>
   <Vij>0.0</Vij>
   <Vij>0.0</Vij>
   <Vij>0.0</Vij>
   <Vij>9.059834154394386e-06</Vij>
   <Vij>4.074184769296532</Vij>
   <Vij>0.0</Vij>
   <Vij>0.0</Vij>
   <Vij>0.0</Vij>
   <Vij>0.8513879487290978</Vij>
   <Vij>0.37235918373335153</Vij>
   <Vij>1.8119668308788772e-05</Vij>
   <Vij>0.10287441682314824</Vij>
   <Vij>-0.006341883912682533</Vij>
   <Vij>1.6496019188314894</Vij>
   <Vij>9.059834154394386e-06</Vij>
   <Vij>1.6496019188314894</Vij>
   <Vij>0.10522997367661446</Vij>
   <Vij>0.0</Vij>
   <Vij>0.00634188390807607</Vij>
   <Vij>0.0</Vij>
   <Vij>0.0</Vij>
   <Vij>-0.21103295020293444</Vij>
   <Vij>0.0</Vij>
   <Vij>0.0</Vij>
   <Vij>5.345302151115635e-05</Vij>
   <Vij>0.0</Vij>
   <Vij>0.0</Vij>
   <Vij>0.0</Vij>
   <Vij>0.0</Vij>
   <Vij>0.0</Vij>
   <Vij>0.0</Vij>
   <Vij>0.0</Vij>
   <Vij>0.0</Vij>
   <Vij>0.0</Vij>
   <Vij>0.0</Vij>
   <Vij>0.0</Vij>
   <Vij>0.0</Vij>
   <Vij>0.0</Vij>
   <Vij>0.0</Vij>
   <Vij>0.0</Vij>
   <Vij>-0.048923104419372976</Vij>
   <Vij>0.0</Vij>
   <Vij>0.0</Vij>
   <Vij>2.6527597891543278</Vij>
   <Vij>0.0</Vij>
   <Vij>2.6527597891399637</Vij>
   <Vij>0.0</Vij>
   <Vij>0.04892310443372968</Vij>
   <Vij>0.0</Vij>
   <Vij>0.0</Vij>
   <Vij>0.294453184469603</Vij>
   <Vij>0.0</Vij>
   <Vij>0.0</Vij>
   <Vij>0.0</Vij>
   <Vij>0.21114758879411966</Vij>
   <Vij>0.2111475888189003</Vij>
   <Vij>0.0</Vij>
   <Vij>3.0287335553439334</Vij>
   <Vij>0.0</Vij>
   <Vij>0.0</Vij>
   <Vij>0.0</Vij>
   <Vij>0.0</Vij>
   <Vij>0.0</Vij>
   <Vij>-0.11868382745888084</Vij>
   <Vij>0.0</Vij>
   <Vij>0.0</Vij>
   <Vij>0.015220521379382566</Vij>
   <Vij>0.0</Vij>
   <Vij>0.0</Vij>
   <Vij>0.0</Vij>
   <Vij>0.0</Vij>
   <Vij>0.025005142266128502</Vij>
   <Vij>0.0</Vij>
   <Vij>0.0</Vij>
   <Vij>0.0</Vij>
   <Vij>0.023011978752161738</Vij>
   <Vij>0.015220521367155015</Vij>
   <Vij>0.0</Vij>
   <Vij>0.0</Vij>
   <Vij>0.0</Vij>
   <Vij>0.0</Vij>
   <Vij>0.025005142266128502</Vij>
   <Vij>0.06523080591163957</Vij>
   <Vij>0.007610260689691283</Vij>
   <Vij>0.025005142266128502</Vij>
   <Vij>0.0</Vij>
   <Vij>0.022377790361354132</Vij>
   <Vij>0.0</Vij>
   <Vij>0.32035573569938547</Vij>
   <Vij>999999.0</Vij>
   <Vij>0.025005142266128502</Vij>
   <Vij>0.025005142266128502</Vij>
   <Vij>0.025005142266128502</Vij>
   <Vij>0.025005142266128502</Vij>
   <Vij>0.0</Vij>
   <Vij>-999999.0</Vij>
   <Vij>0.0</Vij>
   <Vij>0.0</Vij>
   <Vij>0.21024975913778784</Vij>
   <Vij>0.0</Vij>
   <Vij>0.0</Vij>
   <Vij>-0.18723778042476624</Vij>
   <Vij>0.0</Vij>
   <Vij>0.0</Vij>
   <Vij>0.25005142266128505</Vij>
   <Vij>0.0</Vij>
   <Vij>0.0</Vij>
   <Vij>0.025005142266128502</Vij>
   <Vij>0.015220521379382566</Vij>
   <Vij>0.2811556453965635</Vij>
   <Vij>0.0</Vij>
   <Vij>-999999.0</Vij>
   <Vij>0.31809077714569867</Vij>
   <Vij>0.022377790361354132</Vij>
   <Vij>0.00634188390807607</Vij>
   <Vij>999999.0</Vij>
   <Vij>0.0</Vij>
   <Vij>0.0</Vij>
   <Vij>5.70793870894704</Vij>
   <Vij>0.0</Vij>
   <Vij>0.0</Vij>
   <Vij>3.0515643373364583</Vij>
   <Vij>2.6563743714941666</Vij>
   <Vij>0.0</Vij>
   <Vij>0.0</Vij>
   <Vij>0.0</Vij>
   <Vij>999999.0</Vij>
   <Vij>-999999.0</Vij>
   <Vij>0.0</Vij>
   <Vij>-4.096531950403005</Vij>
   <Vij>0.0</Vij>
   <Vij>0.0</Vij>
   <Vij>0.0</Vij>
   <Vij>0.0</Vij>
   <Vij>-0.022377790417522192</Vij>
   <Vij>0.0</Vij>
   <Vij>0.0</Vij>
   <Vij>0.0</Vij>
   <Vij>0.022377790361354132</Vij>
   <Vij>0.022830782069073848</Vij>
   <Vij>0.0</Vij>
   <Vij>0.0</Vij>
   <Vij>0.0</Vij>
   <Vij>0.007610260689691283</Vij>
   <Vij>0.0</Vij>
   <Vij>999998.1186593333</Vij>
   <Vij>0.0</Vij>
   <Vij>0.0</Vij>
   <Vij>0.0</Vij>
   <Vij>5.467825924279168</Vij>
   <Vij>0.48916490743155816</Vij>
   <Vij>0.0</Vij>
   <Vij>999998.4828646665</Vij>
   <Vij>0.2111475888189003</Vij>
   <Vij>0.0</Vij>
   <Vij>0.0</Vij>
   <Vij>0.0</Vij>
   <Vij>0.0</Vij>
   <Vij>0.0</Vij>
   <Vij>0.0</Vij>
   <Vij>0.0</Vij>
   <Vij>0.0</Vij>
   <Vij>0.0</Vij>
   <Vij>0.0</Vij>
   <Vij>0.0</Vij>
   <Vij>0.0</Vij>
   <Vij>0.0</Vij>
   <Vij>0.0</Vij>
   <Vij>0.0</Vij>
   <Vij>0.0</Vij>
   <Vij>0.32035573569938547</Vij>
   <Vij>-0.32035573571920395</Vij>
   <Vij>0.0</Vij>
   <Vij>0.0</Vij>
   <Vij>0.21114758879411966</Vij>
   <Vij>0.0</Vij>
   <Vij>0.0</Vij>
   <Vij>0.0</Vij>
   <Vij>0.0</Vij>
   <Vij>0.0</Vij>
   <Vij>0.0</Vij>
   <Vij>0.0</Vij>
   <Vij>0.0</Vij>
   <Vij>0.0</Vij>
   <Vij>0.37235918373335153</Vij>
   <Vij>0.3723591837456093</Vij>
   <Vij>0.132273578654158</Vij>
   <Vij>0.0</Vij>
   <Vij>0.0</Vij>
   <Vij>0.0</Vij>
   <Vij>0.0</Vij>
   <Vs>0.0</Vs>
   <Vs>0.0</Vs>
   <Vs>0.0</Vs>
   <Vs>0.0</Vs>
   <Vs>0.0</Vs>
   <Vs>0.0</Vs>
   <Vs>0.0</Vs>
   <Vs>0.0</Vs>
   <Vs>0.0</Vs>
   <Vs>0.0</Vs>
   <Vs>0.0</Vs>
   <Vs>0.0</Vs>
   <Vs>0.0</Vs>
   <Vs>0.0</Vs>
   <Vs>0.0</Vs>
   <Vs>0.0</Vs>
   <Vs>0.0</Vs>
   <Vs>0.0</Vs>
   <Vs>0.0</Vs>
   <Vs>0.0</Vs>
   <Vs>0.0</Vs>
   <Vs>0.0</Vs>
   <Vs>0.0</Vs>
   <Vs>0.0</Vs>
   <Vs>0.0</Vs>
   <Vs>0.0</Vs>
   <Vs>0.0</Vs>
   <Vs>0.004978519713273084</Vs>
   <Vs>0.0</Vs>
   <Vs>0.004978519713273084</Vs>
   <Vs>0.0</Vs>
   <Vs>0.0</Vs>
   <Vs>0.0</Vs>
   <Vs>0.21267378803374212</Vs>
   <Vs>0.0</Vs>
   <Vs>0.0</Vs>
   <Vs>0.0</Vs>
   <Vs>0.0</Vs>
   <Vs>0.0</Vs>
   <Vs>0.02977892347013345</Vs>
   <Vs>0.02977892347013345</Vs>
   <Vs>0.025445767423395764</Vs>
   <Vs>0.0</Vs>
   <Vs>0.05281462637825752</Vs>
   <Vs>0.0765271313829582</Vs>
   <Vs>0.0</Vs>
   <Vs>0.0</Vs>
   <Vs>0.0</Vs>
   <Vs>0.0</Vs>
   <Vs>0.0</Vs>
   <Vs>0.0</Vs>
   <Vs>0.0</Vs>
   <Vs>0.0</Vs>
   <Vs>0.0</Vs>
   <Vs>0.0</Vs>
   <Vs>0.0</Vs>
   <Vs>0.0</Vs>
   <Vs>0.0</Vs>
   <Vs>0.029622192293974847</Vs>
   <Vs>0.02977892347013345</Vs>
   <Vs>0.0</Vs>
   <Vs>0.0</Vs>
   <Vs>3.0232944403227684</Vs>
   <Vs>-0.02977892347013345</Vs>
   <Vs>0.0</Vs>
   <Vs>0.0</Vs>
   <Vs>0.0038721819992123983</Vs>
   <Vs>0.0</Vs>
   <Vs>0.0</Vs>
   <Vs>0.0</Vs>
   <Vs>0.0</Vs>
   <Vs>0.0</Vs>
   <Vs>0.004609740475252852</Vs>
   <Vs>0.004609740475252852</Vs>
   <Vs>0.0</Vs>
   <Vs>0.0</Vs>
   <Vs>0.0</Vs>
   <Vs>0.0</Vs>
   <Vs>0.0</Vs>
   <Vs>0.0</Vs>
   <Vs>0.0</Vs>
   <Vs>0.0</Vs>
   <Vs>0.0</Vs>
   <Vs>999999.0</Vs>
   <Vs>-999998.7870782996</Vs>
   <Vs>0.0</Vs>
   <Vs>0.0</Vs>
   <Vs>0.0006453636665353998</Vs>
   <Vs>0.02590674147092105</Vs>
   <Vs>0.0</Vs>
   <Vs>0.02590674147092105</Vs>
   <Vs>0.0006453636665354062</Vs>
   <Vs>0.0</Vs>
   <Vs>0.0038721819992123983</Vs>
   <Vs>0.0</Vs>
   <Vs>0.0</Vs>
   <Vs>0.0</Vs>
   <Vs>-0.04606052682872653</Vs>
   <Vs>0.0</Vs>
   <Vs>0.0</Vs>
   <Vs>0.0</Vs>
   <Vs>0.02148683010843911</Vs>
   <Vs>0.026690305365442556</Vs>
   <Vs>0.04405980747619531</Vs>
   <Vs>0.026690305365442556</Vs>
   <Vs>0.0</Vs>
   <Vs>0.001273947877740879</Vs>
   <Vs>0.0012487786947459984</Vs>
   <Vs>0.008991206602171188</Vs>
   <Vs>0.001748290172644398</Vs>
   <Vs>0.012487786947459984</Vs>
   <Vs>0.0</Vs>
   <Vs>0.002323309199527439</Vs>
   <Vs>0.0</Vs>
   <Vs>0.0</Vs>
   <Vs>-0.02977892347013345</Vs>
   <Vs>0.02111261137665808</Vs>
   <Vs>0.0</Vs>
   <Vs>0.0</Vs>
   <Vs>0.0</Vs>
   <Vs>0.0</Vs>
   <Vs>0.0</Vs>
   <Vs>0.0</Vs>
   <Vs>5.439493760805991e-06</Vs>
   <Vs>0.0</Vs>
   <Vs>0.0</Vs>
   <Vs>0.05235734033165045</Vs>
   <Vs>0.04405980747619531</Vs>
   <Vs>-0.04405980747619531</Vs>
   <Vs>1.4147132181805178</Vs>
   <Vs>0.02905058447504349</Vs>
   <Vs>0.0</Vs>
   <Vs>0.0025445767423395763</Vs>
   <Vs>0.005089153484679153</Vs>
   <Vs>0.0</Vs>
   <Vs>0.0</Vs>
   <Vs>0.054957325945964544</Vs>
   <Vs>0.0</Vs>
   <Vs>0.0</Vs>
   <Vs>0.0</Vs>
   <Vs>-0.0526247972654866</Vs>
   <Vs>0.0</Vs>
   <Vs>0.04606052682872653</Vs>
   <Vs>0.0</Vs>
   <Vs>0.028303806518052532</Vs>
   <Vs>0.014036659747144943</Vs>
   <Vs>0.0</Vs>
   <Vs>0.037892066706578464</Vs>
   <Vs>0.0</Vs>
   <Vs>0.0</Vs>
   <Vs>0.0</Vs>
   <Vs>0.0</Vs>
   <Vs>0.0002516918299522164</Vs>
   <Vs>0.0</Vs>
   <Vs>1.8438961901011423e-06</Vs>
   <Vs>0.0005946565213076183</Vs>
   <Vs>0.0</Vs>
   <Vs>0.0</Vs>
   <Vs>0.0</Vs>
   <Vs>6.42257508084567</Vs>
   <Vs>0.0</Vs>
   <Vs>0.0</Vs>
   <Vs>0.0</Vs>
   <Vs>-0.21425031969335817</Vs>
   <Vs>0.0</Vs>
   <Vs>0.0</Vs>
   <Vs>0.0</Vs>
   <Vs>0.0</Vs>
   <Vs>0.0</Vs>
   <Vs>0.0</Vs>
   <Vs>0.0</Vs>
   <Vs>0.0</Vs>
   <Vs>0.0</Vs>
   <Vs>0.0</Vs>
   <Vs>3.0232944403227684</Vs>
   <Vs>0.0</Vs>
   <Vs>0.0</Vs>
   <Vs>0.037892066706578464</Vs>
   <Vs>0.0</Vs>
   <Vs>-0.047664716514114525</Vs>
   <Vs>0.0</Vs>
   <Vs>0.0</Vs>
   <Vs>0.0765271313829582</Vs>
   <Vs>0.025445767423395764</Vs>
   <Vs>0.013958294159065642</Vs>
   <Vs>0.0</Vs>
   <Vs>0.0</Vs>
   <Vs>0.0</Vs>
   <Vs>0.0</Vs>
   <Vs>0.0</Vs>
   <Vs>0.0</Vs>
   <Vs>0.0</Vs>
   <Vs>0.0</Vs>
   <Vs>0.0</Vs>
   <Vs>0.02148683010843911</Vs>
   <Vs>0.013460442187738337</Vs>
   <Vs>0.0</Vs>
   <Vs>0.0</Vs>
   <Vs>0.0</Vs>
   <Vs>0.032600084640988194</Vs>
   <Vs>0.0</Vs>
   <Vs>0.0</Vs>
   <Vs>0.0</Vs>
   <Vs>2.4338997522775583</Vs>
   <Vs>0.0</Vs>
   <Vs>0.0</Vs>
   <Vs>0.0</Vs>
   <Vs>0.032600084640988194</Vs>
   <Vs>0.006886952270027762</Vs>
   <Vs>0.004609740475252852</Vs>
   <Vs>0.0</Vs>
   <Vs>7.6</Vs>
   <Vs>0.004609740475252852</Vs>
   <Vs>0.0</Vs>
   <Vs>0.0</Vs>
   <Vs>0.01636540844043319</Vs>
   <Vs>0.0</Vs>
   <Vs>0.02905058447504349</Vs>
   <Vs>-0.02905058447504349</Vs>
   <Vs>0.008297532855455139</Vs>
   <Vs>0.0</Vs>
   <Vs>0.0</Vs>
   <Vs>7.15318740347843</Vs>
   <Vs>0.0</Vs>
   <Vs>0.0</Vs>
   <Vs>0.0</Vs>
   <Vs>0.004609740475252852</Vs>
   <Vs>0.0</Vs>
   <Vs>0.0</Vs>
   <Vs>0.037892066706578464</Vs>
   <Vs>0.0</Vs>
   <Vs>0.0</Vs>
   <Vs>0.0015488727996849593</Vs>
   <Vs>0.0</Vs>
   <Vs>0.037892066706578464</Vs>
   <Vs>0.0</Vs>
   <Vs>0.03005550789864862</Vs>
   <Vs>0.0</Vs>
   <Vs>0.032600084640988194</Vs>
   <Vs>0.0</Vs>
   <Vs>0.0</Vs>
   <Vs>0.0</Vs>
   <Vs>0.0006453636665353998</Vs>
   <Vs>0.0</Vs>
   <Vs>0.02148683010843911</Vs>
   <Vs>0.0</Vs>
   <Vs>0.0</Vs>
   <Vs>0.0</Vs>
   <Vs>0.0</Vs>
   <Vs>0.0</Vs>
   <Vs>0.0007744363998424796</Vs>
   <Vs>0.0</Vs>
   <Vs>0.0</Vs>
   <Vs>0.0</Vs>
   <Vs>0.0007744363998424796</Vs>
   <Vs>0.0</Vs>
   <Vs>0.0</Vs>
   <Vs>0.0</Vs>
   <Vs>0.0</Vs>
   <Vs>0.0</Vs>
   <Vs>19.508055902241267</Vs>
   <Vs>0.004609740475252852</Vs>
   <Vs>0.0</Vs>
   <Vs>0.004609740475252852</Vs>
   <Vs>0.0</Vs>
   <Vs>0.0</Vs>
   <Vs>0.0</Vs>
   <Vs>5.439493760805991e-06</Vs>
   <Vs>0.09219480950505711</Vs>
   <Vs>5.439493760805991e-06</Vs>
   <Vs>0.0</Vs>
   <Vs>0.0</Vs>
   <Vs>0.047664716514114525</Vs>
   <Vs>11.179236950921783</Vs>
   <Vs>0.0</Vs>
   <Vs>0.0022772117947749107</Vs>
   <Vs>0.0</Vs>
   <Vs>0.0</Vs>
   <Vs>0.0</Vs>
   <Vs>0.0</Vs>
   <Vs>0.0</Vs>
   <Vs>0.0</Vs>
   <Vs>0.0</Vs>
   <Vs>0.0</Vs>
   <Vs>0.0</Vs>
   <Vs>0.0</Vs>
   <Vs>0.0</Vs>
   <Vs>0.0</Vs>
   <Vs>0.0</Vs>
   <Vs>0.0</Vs>
   <Vs>0.0</Vs>
   <Vs>0.0</Vs>
   <Vs>32.14289375183813</Vs>
   <Vs>0.0</Vs>
   <Vs>0.0</Vs>
   <Vs>0.0</Vs>
   <Vs>0.0</Vs>
   <Vs>0.0</Vs>
   <Vs>0.0</Vs>
   <Vs>0.0</Vs>
   <Vs>0.0</Vs>
   <Vs>0.0</Vs>
   <Vs>0.0</Vs>
   <Vs>0.0</Vs>
   <Vs>0.0</Vs>
   <Vs>0.0</Vs>
   <Vs>0.0</Vs>
   <Vs>0.0</Vs>
   <Vs>0.0</Vs>
   <Vs>0.0</Vs>
   <Vs>0.0</Vs>
   <Vs>0.0</Vs>
   <Vs>0.0</Vs>
   <Vs>0.0</Vs>
   <Vs>0.0</Vs>
   <Vs>0.0</Vs>
   <Vs>0.0</Vs>
   <Vs>0.0</Vs>
   <Vs>0.0</Vs>
   <Vs>0.0</Vs>
   <Vs>0.0</Vs>
   <Vs>0.0</Vs>
   <Vs>0.0</Vs>
   <Vs>0.0</Vs>
   <Vs>0.0</Vs>
   <Vs>0.0</Vs>
   <Vs>0.0</Vs>
   <Vs>0.0</Vs>
   <Vs>0.0</Vs>
   <Vs>0.0</Vs>
   <Vs>-6.42257508084567</Vs>
   <Vs>0.0</Vs>
   <Vs>0.0</Vs>
   <Vs>0.03386886940085876</Vs>
   <Vs>9.219480950505711e-07</Vs>
   <Vs>0.0</Vs>
   <Vs>0.0</Vs>
   <Vs>0.0</Vs>
   <Vs>0.0</Vs>
   <Vs>0.0</Vs>
   <Vs>0.0</Vs>
   <Vs>0.0</Vs>
   <Vs>0.0</Vs>
   <Vs>0.0</Vs>
   <Vs>0.02905058447504349</Vs>
   <Vs>0.0</Vs>
   <Vs>12.699866536301398</Vs>
   <Vs>0.0</Vs>
   <Vs>0.0</Vs>
   <Vs>0.0</Vs>
   <Vs>0.0</Vs>
   <Vs>0.0</Vs>
   <Vs>0.0</Vs>
   <Vs>0.0</Vs>
   <Vs>0.028611921362880405</Vs>
   <Vs>0.0</Vs>
   <Vs>0.0</Vs>
   <Vs>0.0</Vs>
   <Vs>-12.632511958293836</Vs>
   <Vs>0.0</Vs>
   <Vs>0.0</Vs>
   <Vs>0.0</Vs>
   <Vs>0.0</Vs>
   <Vs>0.0</Vs>
   <Vs>0.0</Vs>
   <Vs>0.0</Vs>
   <Vs>0.0</Vs>
   <Vs>0.006638026284364112</Vs>
   <Vs>0.0</Vs>
   <Vs>0.0</Vs>
   <Vs>0.0</Vs>
   <Vs>0.0</Vs>
   <Vs>0.0</Vs>
   <Vs>0.0</Vs>
   <Vs>0.0</Vs>
   <Vs>0.0</Vs>
   <Vs>0.0</Vs>
   <Vs>0.0</Vs>
   <Vs>-0.015221363049284928</Vs>
   <Vs>0.0</Vs>
   <Vs>0.0</Vs>
   <Vs>0.0</Vs>
   <Vs>0.0</Vs>
   <Vs>0.0</Vs>
   <Vs>0.0</Vs>
   <Vs>0.0</Vs>
   <Vs>0.019360909996061992</Vs>
   <Vs>0.019360909996061992</Vs>
   <Vs>0.0</Vs>
   <Vs>0.0</Vs>
   <Vs>0.0</Vs>
   <Vs>0.0</Vs>
   <Vs>0.0</Vs>
   <Vs>0.0</Vs>
   <Vs>0.0</Vs>
   <Vs>0.0</Vs>
   <Vs>0.0</Vs>
   <Vs>-10.0</Vs>
   <Vs>0.0</Vs>
   <Vs>0.0</Vs>
   <Vs>0.0</Vs>
   <Vs>0.0</Vs>
   <Vs>0.0</Vs>
   <Vs>0.0</Vs>
   <Vs>0.0</Vs>
   <Vs>0.0</Vs>
   <Vs>0.0</Vs>
   <Vs>0.0</Vs>
   <Vs>0.0</Vs>
   <Vs>0.0</Vs>
   <Vs>0.0</Vs>
   <Vs>0.0</Vs>
   <Vs>0.0</Vs>
   <Vs>0.0</Vs>
   <Vs>0.0</Vs>
   <Vs>0.0</Vs>
   <Vs>0.0</Vs>
   <Vs>0.0018254572282001306</Vs>
   <Vs>0.0</Vs>
   <Vs>0.0</Vs>
   <Vs>0.0</Vs>
   <Vs>0.0</Vs>
   <Vs>0.0</Vs>
   <Vs>0.0</Vs>
   <Vs>0.0</Vs>
   <Vs>0.0</Vs>
   <Vs>0.0</Vs>
   <Vs>19.704532998544508</Vs>
   <Vs>0.04405980747619531</Vs>
   <Vs>0.0</Vs>
   <Vs>0.0</Vs>
   <Vs>0.004609740475252852</Vs>
   <Vs>0.0</Vs>
   <Vs>0.0</Vs>
   <Vs>0.014198000663778795</Vs>
   <Vs>0.0</Vs>
   <Vs>0.0</Vs>
   <Vs>0.006638026284364112</Vs>
   <Vs>0.14538190312225308</Vs>
   <Vs>0.07333175148032242</Vs>
   <Vs>5.066597698957789</Vs>
   <Vs>0.0</Vs>
   <Vs>0.0</Vs>
   <Vs>0.0</Vs>
   <Vs>4.933402301042211</Vs>
   <Vs>0.0</Vs>
   <Vs>0.014198000663778795</Vs>
   <Vs>0.17531746578227364</Vs>
   <Vs>0.0</Vs>
   <Vs>0.0</Vs>
   <Vs>0.0</Vs>
   <Vs>0.0</Vs>
   <Vs>0.0</Vs>
   <Vs>0.0</Vs>
   <Vs>0.019360909996061992</Vs>
   <Vs>0.0</Vs>
   <Vs>0.0</Vs>
   <Vs>0.0</Vs>
   <Vs>0.0</Vs>
   <Vs>0.0</Vs>
   <Vs>0.0</Vs>
   <Vs>-0.7673369391621603</Vs>
   <Vs>0.0</Vs>
   <Vs>0.04405980747619531</Vs>
   <Vs>0.0</Vs>
   <Vs>0.0</Vs>
   <Vs>0.0</Vs>
   <Vs>0.0</Vs>
   <Vs>-0.0025445767423395763</Vs>
   <Vs>0.0</Vs>
   <Vs>0.0</Vs>
   <Vs>0.0</Vs>
   <Vs>0.0</Vs>
   <Vs>0.0</Vs>
   <Vs>0.0</Vs>
   <Vs>0.0</Vs>
   <Vs>-11.179236950921783</Vs>
   <Vs>-0.9850483441991479</Vs>
   <Vs>0.0</Vs>
   <Vs>0.0</Vs>
   <Vs>0.0</Vs>
   <Vs>0.0</Vs>
   <Vs>0.0</Vs>
   <Vs>0.0</Vs>
   <Vs>0.0</Vs>
   <Vs>0.25673359550993746</Vs>
   <Vs>0.0</Vs>
   <Vs>0.0</Vs>
   <Vs>0.0</Vs>
   <Vs>0.0</Vs>
   <Vs>0.0</Vs>
   <Vs>0.0</Vs>
   <Vs>0.0</Vs>
   <Vs>0.0</Vs>
   <Vs>0.0</Vs>
   <Vs>0.0</Vs>
   <Vs>4.933402301042211</Vs>
   <Vs>0.0</Vs>
   <Vs>0.0</Vs>
   <Vs>-1.2175952398053145</Vs>
   <Vs>0.0</Vs>
   <Vs>0.0</Vs>
   <Vs>0.008297532855455139</Vs>
   <Vs>0.008297532855455139</Vs>
   <Vs>0.0</Vs>
   <Vs>0.0</Vs>
   <Vs>0.0</Vs>
   <Vs>0.0</Vs>
   <Vs>0.0</Vs>
   <Vs>0.0</Vs>
   <Vs>0.0</Vs>
   <Vs>0.0</Vs>
   <Vs>0.0</Vs>
   <Vs>0.004609740475252852</Vs>
   <Vs>0.0</Vs>
   <Vs>0.0</Vs>
   <Vs>0.0</Vs>
   <Vs>0.0</Vs>
   <Vs>0.0005946565213076183</Vs>
   <Vs>0.0</Vs>
   <Vs>-0.0840482005722265</Vs>
   <Vs>0.0</Vs>
   <Vs>0.0</Vs>
   <Vs>0.0</Vs>
   <Vs>0.004609740475252852</Vs>
   <Vs>0.0</Vs>
   <Vs>0.0</Vs>
   <Vs>0.0</Vs>
   <Vs>0.002323309199527439</Vs>
   <Vs>0.002323309199527439</Vs>
   <Vs>0.002323309199527439</Vs>
   <Vs>0.0</Vs>
   <Vs>0.0</Vs>
   <Vs>0.0</Vs>
   <Vs>0.025667034966207897</Vs>
   <Vs>0.0</Vs>
   <Vs>0.0</Vs>
   <Vs>-0.013460442187738337</Vs>
   <Vs>0.0</Vs>
   <Vs>0.013460442187738337</Vs>
   <Vs>0.0</Vs>
   <Vs>0.0</Vs>
   <Vs>0.0</Vs>
   <Vs>0.0</Vs>
   <Vs>0.0</Vs>
   <Vs>0.008297532855455139</Vs>
   <Vs>0.0</Vs>
   <Vs>0.0</Vs>
   <Vs>0.0</Vs>
   <Vs>0.0</Vs>
   <Vs>0.0</Vs>
   <Vs>0.0</Vs>
   <Vs>0.0</Vs>
   <Vs>0.0</Vs>
   <Vs>0.03386886940085876</Vs>
   <Vs>0.0</Vs>
   <Vs>0.0</Vs>
   <Vs>0.0</Vs>
   <Vs>0.047664716514114525</Vs>
   <Vs>0.0</Vs>
   <Vs>0.0</Vs>
   <Vs>0.0</Vs>
   <Vs>1.517104773616834</Vs>
   <Vs>0.0</Vs>
   <Vs>0.0</Vs>
   <Vs>1.5061896667059345</Vs>
   <Vs>0.0</Vs>
   <Vs>0.0</Vs>
   <Vs>0.0</Vs>
   <Vs>0.0</Vs>
   <Vs>0.0</Vs>
   <Vs>0.0</Vs>
   <Vs>0.008297532855455139</Vs>
   <Vs>0.0</Vs>
   <Vs>0.004609740475252852</Vs>
   <Vs>0.008297532855455139</Vs>
   <Vs>0.0</Vs>
   <Vs>0.004978519713273084</Vs>
   <Vs>0.0</Vs>
   <Vs>-0.025445767423395764</Vs>
   <Vs>0.0</Vs>
   <Vs>0.0</Vs>
   <Vs>0.0</Vs>
   <Vs>0.0</Vs>
   <Vs>-0.05235734033165045</Vs>
   <Vs>0.025445767423395764</Vs>
   <Vs>0.0</Vs>
   <Vs>0.029622192293974847</Vs>
   <Vs>0.0</Vs>
   <Vs>0.025667034966207897</Vs>
   <Vs>0.0</Vs>
   <Vs>0.0</Vs>
   <Vs>0.0030977455993699186</Vs>
   <Vs>0.0</Vs>
   <Vs>0.0038721819992123983</Vs>
   <Vs>0.0038721819992123983</Vs>
   <Vs>0.0038721819992123983</Vs>
   <Vs>0.0</Vs>
   <Vs>0.0</Vs>
   <Vs>0.0</Vs>
   <Vs>0.0</Vs>
   <Vs>0.0</Vs>
   <Vs>0.0</Vs>
   <Vs>0.03945937846816444</Vs>
   <Vs>0.0</Vs>
   <Vs>-0.03945937846816444</Vs>
   <Vs>-0.03945937846816444</Vs>
   <Vs>0.03945937846816444</Vs>
   <Vs>0.0</Vs>
   <Vs>0.0</Vs>
   <Vs>0.0</Vs>
   <Vs>-0.0765271313829582</Vs>
   <Vs>-0.02148683010843911</Vs>
   <Vs>0.0</Vs>
   <Vs>0.0</Vs>
   <Vs>0.0</Vs>
   <Vs>0.0</Vs>
   <Vs>0.0</Vs>
   <Vs>15.650071420908416</Vs>
   <Vs>0.0</Vs>
   <Vs>0.0</Vs>
   <Vs>0.0</Vs>
   <Vs>0.03945937846816444</Vs>
   <Vs>0.0</Vs>
   <Vs>0.0006453636665354062</Vs>
   <Vs>0.0</Vs>
   <Vs>0.0</Vs>
   <Vs>0.0</Vs>
   <Vs>0.013460442187738344</Vs>
   <Vs>0.0</Vs>
   <Vs>0.0</Vs>
   <Vs>0.0007744363998424796</Vs>
   <Vs>0.0</Vs>
   <Vs>0.0</Vs>
   <Vs>0.0</Vs>
   <Vs>0.0</Vs>
   <Vs>0.0</Vs>
   <Vs>0.0</Vs>
   <Vs>0.0</Vs>
   <Vs>0.0</Vs>
   <Vs>0.0</Vs>
   <Vs>0.0</Vs>
   <Vs>0.0</Vs>
   <Vs>0.0</Vs>
   <Vs>0.0</Vs>
   <Vs>0.0007744363998424796</Vs>
   <Vs>0.0</Vs>
   <Vs>0.0</Vs>
   <Vs>0.0</Vs>
   <Vs>0.0</Vs>
   <Vs>0.0</Vs>
   <Vs>0.0</Vs>
   <Vs>0.0</Vs>
   <Vs>0.0</Vs>
   <Vs>0.0</Vs>
   <Vs>0.0</Vs>
   <Vs>0.0</Vs>
   <Vs>0.0</Vs>
   <Vs>0.0</Vs>
   <Vs>0.0</Vs>
   <Vs>0.0</Vs>
   <Vs>0.0</Vs>
   <Vs>0.0</Vs>
   <Vs>0.0</Vs>
   <Vs>0.0</Vs>
   <Vs>0.0</Vs>
   <Vs>0.0</Vs>
   <Vs>1.5107994071811879</Vs>
   <Vs>0.0</Vs>
   <Vs>0.0</Vs>
   <Vs>0.0</Vs>
   <Vs>0.0007744363998424796</Vs>
   <Vs>0.0007744363998424796</Vs>
   <Vs>0.0</Vs>
   <Vs>0.0</Vs>
   <Vs>5.439493760805991e-06</Vs>
   <Vs>0.0</Vs>
   <Vs>0.0</Vs>
   <Vs>0.0</Vs>
   <Vs>0.0</Vs>
   <Vs>0.0006453636665353998</Vs>
   <Vs>0.12502906917072615</Vs>
   <Vs>0.0</Vs>
   <Vs>0.0</Vs>
   <Vs>0.0</Vs>
   <Vs>0.12502906917072615</Vs>
   <Vs>0.0</Vs>
   <Vs>0.0180701826629912</Vs>
   <Vs>0.0006453636665353998</Vs>
   <Vs>0.0006453636665353998</Vs>
   <Vs>0.0</Vs>
   <Vs>0.0</Vs>
   <Vs>0.0</Vs>
   <Vs>0.0</Vs>
   <Vs>0.0</Vs>
   <Vs>0.0</Vs>
   <Vs>0.0</Vs>
   <Vs>0.0</Vs>
   <Vs>0.0</Vs>
   <Vs>0.0</Vs>
   <Vs>0.0</Vs>
   <Vs>0.0</Vs>
   <Vs>0.0</Vs>
   <Vs>0.0</Vs>
   <Vs>0.0</Vs>
   <Vs>0.0</Vs>
   <Vs>0.21267378803374212</Vs>
   <Vs>-11.121712551112648</Vs>
   <Vs>2.4338997522775583</Vs>
   <Vs>0.0</Vs>
   <Vs>0.0</Vs>
   <Vs>12.661387926425286</Vs>
   <Vs>0.0</Vs>
   <Vs>0.0</Vs>
   <Vs>4.886324903774497e-05</Vs>
   <Vs>0.0</Vs>
   <Vs>0.0006453636665353998</Vs>
   <Vs>0.0</Vs>
   <Vs>0.0</Vs>
   <Vs>0.0</Vs>
   <Vs>0.0</Vs>
   <Vs>0.0</Vs>
   <Vs>0.0002516918299522164</Vs>
   <Vs>0.0</Vs>
   <Vs>0.0</Vs>
   <Vs>0.0</Vs>
   <Vs>0.0</Vs>
   <Vs>0.0</Vs>
   <Vs>0.0</Vs>
   <Vs>0.0</Vs>
   <Vs>0.0</Vs>
   <Vs>-999998.7155758773</Vs>
   <Vs>0.037237483559092566</Vs>
   <Vs>0.0</Vs>
   <Vs>0.0</Vs>
   <Vs>0.0155725330786897</Vs>
   <Vs>0.0</Vs>
   <Vs>0.0022772117947749107</Vs>
   <Vs>0.0023417481614284503</Vs>
   <Vs>0.0</Vs>
   <Vs>0.0002516918299522164</Vs>
   <Vs>0.0</Vs>
   <Vs>0.0</Vs>
   <Vs>0.0</Vs>
   <Vs>-0.0022772117947749107</Vs>
   <Vs>0.0023417481614284503</Vs>
   <Vs>0.0022772117947749107</Vs>
   <Vs>0.0</Vs>
   <Vs>0.0</Vs>
   <Vs>0.0</Vs>
   <Vs>0.9850483441991479</Vs>
   <Vs>0.0</Vs>
   <Vs>0.0</Vs>
   <Vs>0.0</Vs>
   <Vs>0.0</Vs>
   <Vs>0.0</Vs>
   <Vs>0.0</Vs>
   <Vs>0.0</Vs>
   <Vs>0.0</Vs>
   <Vs>0.0</Vs>
   <Vs>0.0</Vs>
   <Vs>0.0</Vs>
   <Vs>0.0</Vs>
   <Vs>0.0</Vs>
   <Vs>0.0002516918299522164</Vs>
   <Vs>0.0</Vs>
   <Vs>0.0</Vs>
   <Vs>0.0</Vs>
   <Vs>0.0</Vs>
   <Vs>0.0</Vs>
   <Vs>0.0</Vs>
   <Vs>-0.006638026284364112</Vs>
   <Vs>0.0</Vs>
   <Vs>0.19647709630324128</Vs>
   <Vs>0.0</Vs>
   <Vs>0.047664716514114525</Vs>
   <Vs>9.869061919704777</Vs>
   <Vs>0.0</Vs>
   <Vs>0.0</Vs>
   <Vs>9.983976542108017</Vs>
   <Vs>0.0</Vs>
   <Vs>-19.704532998544508</Vs>
   <Vs>0.0</Vs>
   <Vs>0.0</Vs>
   <Vs>-19.508055902241267</Vs>
   <Vs>-0.016023457891978926</Vs>
   <Vs>0.0</Vs>
   <Vs>0.0</Vs>
   <Vs>0.0</Vs>
   <Vs>0.0</Vs>
   <Vs>0.0</Vs>
   <Vs>0.0</Vs>
   <Vs>0.0</Vs>
   <Vs>0.0</Vs>
   <Vs>0.0033282326231325616</Vs>
   <Vs>0.0033282326231325616</Vs>
   <Vs>0.0</Vs>
   <Vs>-0.047664716514114525</Vs>
   <Vs>0.0</Vs>
   <Vs>-0.01622628647289005</Vs>
   <Vs>0.047664716514114525</Vs>
   <Vs>0.0</Vs>
   <Vs>1.2175952398053145</Vs>
   <Vs>0.0</Vs>
   <Vs>0.0</Vs>
   <Vs>0.02590674147092105</Vs>
   <Vs>0.0</Vs>
   <Vs>0.0</Vs>
   <Vs>0.0840482005722265</Vs>
   <Vs>0.0</Vs>
   <Vs>0.0</Vs>
   <Vs>0.0</Vs>
   <Vs>0.0</Vs>
   <Vs>0.0</Vs>
   <Vs>0.0</Vs>
   <Vs>0.0</Vs>
   <Vs>0.0</Vs>
   <Vs>0.0</Vs>
   <Vs>0.0</Vs>
   <Vs>0.0</Vs>
   <Vs>0.0</Vs>
   <Vs>0.0</Vs>
   <Vs>5.439493760805991e-06</Vs>
   <Vs>0.0</Vs>
   <Vs>0.03945937846816444</Vs>
   <Vs>0.0</Vs>
   <Vs>0.0</Vs>
   <Vs>0.0</Vs>
   <Vs>0.0</Vs>
   <Vs>0.02905058447504349</Vs>
   <Vs>0.0</Vs>
   <Vs>0.0</Vs>
   <Vs>0.30970864085674404</Vs>
   <Vs>0.0</Vs>
   <Vs>0.0</Vs>
   <Vs>0.0</Vs>
   <Vs>0.0</Vs>
   <Vs>0.0038721819992123987</Vs>
   <Vs>0.0</Vs>
   <Vs>0.0</Vs>
   <Vs>14.35925731112877</Vs>
   <Vs>5.439493760805991e-06</Vs>
   <Vs>0.0</Vs>
   <Vs>0.0</Vs>
   <Vs>0.0</Vs>
   <Vs>-0.048310080180649924</Vs>
   <Vs>-0.02905058447504349</Vs>
   <Vs>0.0</Vs>
   <Vs>0.0</Vs>
   <Vs>0.047664716514114525</Vs>
   <Vs>5.439493760805991e-06</Vs>
   <Vs>0.0</Vs>
   <Vs>0.0</Vs>
   <Vs>0.019360909996061992</Vs>
   <Vs>0.0</Vs>
   <Vs>0.012077520045162483</Vs>
   <Vs>0.01622628647289005</Vs>
   <Vs>0.0</Vs>
   <Vs>5.439493760805991e-06</Vs>
   <Vs>0.0</Vs>
   <Vs>0.0</Vs>
   <Vs>0.0025445767423395763</Vs>
   <Vs>0.0</Vs>
   <Vs>0.0</Vs>
   <Vs>0.0</Vs>
   <Vs>0.02148683010843911</Vs>
   <Vs>0.0025445767423395763</Vs>
   <Vs>0.0</Vs>
   <Vs>0.04405980747619531</Vs>
   <Vs>0.04405980747619531</Vs>
   <Vs>0.004978519713273084</Vs>
   <Vs>0.008297532855455139</Vs>
   <Vs>0.012487786947459984</Vs>
   <Vs>4.820942969524992</Vs>
   <Vs>0.0</Vs>
   <Vs>0.0</Vs>
   <Vs>0.0</Vs>
   <Vs>0.04405980747619531</Vs>
   <Vs>0.008297532855455139</Vs>
   <Vs>0.04405980747619531</Vs>
   <Vs>0.0</Vs>
   <Vs>0.0002516918299522164</Vs>
   <Vs>0.0015488727996849593</Vs>
   <Vs>0.008297532855455139</Vs>
   <Vs>0.0</Vs>
   <Vs>0.0</Vs>
   <Vs>0.0</Vs>
   <Vs>9.219480950505711e-07</Vs>
   <Vs>9.869061919704777</Vs>
   <Vs>0.0</Vs>
   <Vs>0.0</Vs>
   <Vs>0.0</Vs>
   <Vs>0.08663813634991926</Vs>
   <Vs>0.037892066706578464</Vs>
   <Vs>1.8438961901011423e-06</Vs>
   <Vs>0.010468720619299234</Vs>
   <Vs>-0.0006453636665353998</Vs>
   <Vs>0.19647709630324128</Vs>
   <Vs>9.219480950505711e-07</Vs>
   <Vs>0.19647709630324128</Vs>
   <Vs>0.010708427124012383</Vs>
   <Vs>0.0</Vs>
   <Vs>0.0006453636665353998</Vs>
   <Vs>0.0</Vs>
   <Vs>0.0</Vs>
   <Vs>-0.05281462637825752</Vs>
   <Vs>0.0</Vs>
   <Vs>0.0</Vs>
   <Vs>5.439493760805991e-06</Vs>
   <Vs>0.0</Vs>
   <Vs>0.0</Vs>
   <Vs>0.0</Vs>
   <Vs>0.0</Vs>
   <Vs>0.0</Vs>
   <Vs>0.0</Vs>
   <Vs>0.0</Vs>
   <Vs>0.0</Vs>
   <Vs>0.0</Vs>
   <Vs>0.0</Vs>
   <Vs>0.0</Vs>
   <Vs>0.0</Vs>
   <Vs>0.0</Vs>
   <Vs>0.0</Vs>
   <Vs>0.0</Vs>
   <Vs>-0.004978519713273084</Vs>
   <Vs>0.0</Vs>
   <Vs>-15.650071420908416</Vs>
   <Vs>0.0</Vs>
   <Vs>0.0</Vs>
   <Vs>0.0</Vs>
   <Vs>0.0</Vs>
   <Vs>0.004978519713273084</Vs>
   <Vs>0.0</Vs>
   <Vs>0.0</Vs>
   <Vs>-1.3686524147673627</Vs>
   <Vs>0.0</Vs>
   <Vs>0.0</Vs>
   <Vs>0.0022772117947749107</Vs>
   <Vs>0.02148683010843911</Vs>
   <Vs>0.02148683010843911</Vs>
   <Vs>0.0</Vs>
   <Vs>-0.03519226470614937</Vs>
   <Vs>0.0</Vs>
   <Vs>0.0</Vs>
   <Vs>0.0</Vs>
   <Vs>0.0</Vs>
   <Vs>0.0</Vs>
   <Vs>-0.012077520045162483</Vs>
   <Vs>0.050006464675542976</Vs>
   <Vs>0.0</Vs>
   <Vs>0.0015488727996849593</Vs>
   <Vs>0.0</Vs>
   <Vs>0.0</Vs>
   <Vs>0.0</Vs>
   <Vs>0.0</Vs>
   <Vs>0.0025445767423395763</Vs>
   <Vs>0.0</Vs>
   <Vs>0.0</Vs>
   <Vs>0.0</Vs>
   <Vs>0.0023417481614284503</Vs>
   <Vs>0.0015488727996849593</Vs>
   <Vs>0.0</Vs>
   <Vs>0.0</Vs>
   <Vs>0.0</Vs>
   <Vs>0.0</Vs>
   <Vs>0.0025445767423395763</Vs>
   <Vs>0.006638026284364112</Vs>
   <Vs>0.0007744363998424796</Vs>
   <Vs>0.0025445767423395763</Vs>
   <Vs>0.0</Vs>
   <Vs>0.0</Vs>
   <Vs>0.0</Vs>
   <Vs>0.032600084640988194</Vs>
   <Vs>0.0</Vs>
   <Vs>0.0025445767423395763</Vs>
   <Vs>0.0025445767423395763</Vs>
   <Vs>0.0025445767423395763</Vs>
   <Vs>0.0025445767423395763</Vs>
   <Vs>0.0</Vs>
   <Vs>0.0</Vs>
   <Vs>0.0</Vs>
   <Vs>0.0</Vs>
   <Vs>0.0</Vs>
   <Vs>0.0</Vs>
   <Vs>0.0</Vs>
   <Vs>-0.047664716514114525</Vs>
   <Vs>0.0</Vs>
   <Vs>0.0</Vs>
   <Vs>0.025445767423395764</Vs>
   <Vs>0.0</Vs>
   <Vs>0.0</Vs>
   <Vs>0.0025445767423395763</Vs>
   <Vs>0.0015488727996849593</Vs>
   <Vs>0.0</Vs>
   <Vs>0.0</Vs>
   <Vs>0.0</Vs>
   <Vs>0.03236959761722555</Vs>
   <Vs>0.0022772117947749107</Vs>
   <Vs>0.0006453636665353998</Vs>
   <Vs>0.0</Vs>
   <Vs>0.0</Vs>
   <Vs>0.0</Vs>
   <Vs>-0.10595328691934976</Vs>
   <Vs>0.0</Vs>
   <Vs>0.0</Vs>
   <Vs>-0.03286895550662193</Vs>
   <Vs>-0.07308433141272784</Vs>
   <Vs>0.0</Vs>
   <Vs>0.0</Vs>
   <Vs>0.0</Vs>
   <Vs>0.0</Vs>
   <Vs>0.0</Vs>
   <Vs>0.0</Vs>
   <Vs>-0.10207926102394725</Vs>
   <Vs>0.0</Vs>
   <Vs>0.0</Vs>
   <Vs>0.0</Vs>
   <Vs>0.0</Vs>
   <Vs>-0.0022772117947749107</Vs>
   <Vs>0.0</Vs>
   <Vs>0.0</Vs>
   <Vs>0.0</Vs>
   <Vs>0.0022772117947749107</Vs>
   <Vs>0.002323309199527439</Vs>
   <Vs>0.0</Vs>
   <Vs>0.0</Vs>
   <Vs>0.0</Vs>
   <Vs>0.0007744363998424796</Vs>
   <Vs>0.0</Vs>
   <Vs>-0.03706231342103296</Vs>
   <Vs>0.0</Vs>
   <Vs>0.0</Vs>
   <Vs>0.0</Vs>
   <Vs>9.85358886482554</Vs>
   <Vs>0.07838946653496036</Vs>
   <Vs>0.0</Vs>
   <Vs>0.0</Vs>
   <Vs>0.02148683010843911</Vs>
   <Vs>0.0</Vs>
   <Vs>0.0</Vs>
   <Vs>0.0</Vs>
   <Vs>0.0</Vs>
   <Vs>0.0</Vs>
   <Vs>0.0</Vs>
   <Vs>0.0</Vs>
   <Vs>0.0</Vs>
   <Vs>0.0</Vs>
   <Vs>0.0</Vs>
   <Vs>0.0</Vs>
   <Vs>0.0</Vs>
   <Vs>0.0</Vs>
   <Vs>0.0</Vs>
   <Vs>0.0</Vs>
   <Vs>0.0</Vs>
   <Vs>0.032600084640988194</Vs>
   <Vs>-0.032600084640988194</Vs>
   <Vs>0.0</Vs>
   <Vs>0.0</Vs>
   <Vs>0.02148683010843911</Vs>
   <Vs>0.0</Vs>
   <Vs>0.0</Vs>
   <Vs>0.0</Vs>
   <Vs>0.0</Vs>
   <Vs>0.0</Vs>
   <Vs>0.0</Vs>
   <Vs>0.0</Vs>
   <Vs>0.0</Vs>
   <Vs>0.0</Vs>
   <Vs>0.037892066706578464</Vs>
   <Vs>0.037892066706578464</Vs>
   <Vs>0.013460442187738337</Vs>
   <Vs>0.0</Vs>
   <Vs>0.0</Vs>
   <Vs>0.0</Vs>
   <Vs>0.0</Vs>
   <Ys>1.0</Ys>
   <Ys>1.0</Ys>
   <Ys>1.0</Ys>
   <Ys>1.0</Ys>
   <Ys>1.0</Ys>
   <Ys>1.0</Ys>
   <Ys>1.0</Ys>
   <Ys>1.0</Ys>
   <Ys>1.0</Ys>
   <Ys>1.0</Ys>
   <Ys>1.0</Ys>
   <Ys>1.0</Ys>
   <Ys>1.0</Ys>
   <Ys>1.0</Ys>
   <Ys>1.0</Ys>
   <Ys>1.0</Ys>
   <Ys>1.0</Ys>
   <Ys>1.0</Ys>
   <Ys>1.0</Ys>
   <Ys>1.0</Ys>
   <Ys>1.0</Ys>
   <Ys>1.0</Ys>
   <Ys>1.0</Ys>
   <Ys>1.0</Ys>
   <Ys>1.0</Ys>
   <Ys>1.0</Ys>
   <Ys>1.0</Ys>
   <Ys>1.0</Ys>
   <Ys>1.0</Ys>
   <Ys>1.0</Ys>
   <Ys>1.0</Ys>
   <Ys>1.0</Ys>
   <Ys>1.0</Ys>
   <Ys>1.0</Ys>
   <Ys>1.0</Ys>
   <Ys>1.0</Ys>
   <Ys>1.0</Ys>
   <Ys>1.0</Ys>
   <Ys>1.0</Ys>
   <Ys>1.0</Ys>
   <Ys>1.0</Ys>
   <Ys>1.0</Ys>
   <Ys>1.0</Ys>
   <Ys>1.0</Ys>
   <Ys>1.0</Ys>
   <Ys>1.0</Ys>
   <Ys>1.0</Ys>
   <Ys>1.0</Ys>
   <Ys>1.0</Ys>
   <Ys>1.0</Ys>
   <Ys>1.0</Ys>
   <Ys>1.0</Ys>
   <Ys>1.0</Ys>
   <Ys>1.0</Ys>
   <Ys>1.0</Ys>
   <Ys>1.0</Ys>
   <Ys>1.0</Ys>
   <Ys>1.0</Ys>
   <Ys>1.0</Ys>
   <Ys>1.0</Ys>
   <Ys>1.0</Ys>
   <Ys>1.0</Ys>
   <Ys>1.0</Ys>
   <Ys>1.0</Ys>
   <Ys>1.0</Ys>
   <Ys>1.0</Ys>
   <Ys>1.0</Ys>
   <Ys>1.0</Ys>
   <Ys>1.0</Ys>
   <Ys>1.0</Ys>
   <Ys>1.0</Ys>
   <Ys>1.0</Ys>
   <Ys>1.0</Ys>
   <Ys>1.0</Ys>
   <Ys>1.0</Ys>
   <Ys>1.0</Ys>
   <Ys>1.0</Ys>
   <Ys>1.0</Ys>
   <Ys>1.0</Ys>
   <Ys>1.0</Ys>
   <Ys>1.0</Ys>
   <Ys>1.0</Ys>
   <Ys>1.0</Ys>
   <Ys>1.0</Ys>
   <Ys>1.0</Ys>
   <Ys>1.0</Ys>
   <Ys>1.0</Ys>
   <Ys>1.0</Ys>
   <Ys>1.0</Ys>
   <Ys>1.0</Ys>
   <Ys>1.0</Ys>
   <Ys>1.0</Ys>
   <Ys>1.0</Ys>
   <Ys>1.0</Ys>
   <Ys>1.0</Ys>
   <Ys>1.0</Ys>
   <Ys>1.0</Ys>
   <Ys>1.0</Ys>
   <Ys>1.0</Ys>
   <Ys>1.0</Ys>
   <Ys>1.0</Ys>
   <Ys>1.0</Ys>
   <Ys>1.0</Ys>
   <Ys>1.0</Ys>
   <Ys>1.0</Ys>
   <Ys>1.0</Ys>
   <Ys>1.0</Ys>
   <Ys>1.0</Ys>
   <Ys>1.0</Ys>
   <Ys>1.0</Ys>
   <Ys>1.0</Ys>
   <Ys>1.0</Ys>
   <Ys>1.0</Ys>
   <Ys>1.0</Ys>
   <Ys>1.0</Ys>
   <Ys>1.0</Ys>
   <Ys>1.0</Ys>
   <Ys>1.0</Ys>
   <Ys>1.0</Ys>
   <Ys>1.0</Ys>
   <Ys>1.0</Ys>
   <Ys>1.0</Ys>
   <Ys>1.0</Ys>
   <Ys>1.0</Ys>
   <Ys>1.0</Ys>
   <Ys>1.0</Ys>
   <Ys>1.0</Ys>
   <Ys>1.0</Ys>
   <Ys>1.0</Ys>
   <Ys>1.0</Ys>
   <Ys>1.0</Ys>
   <Ys>1.0</Ys>
   <Ys>1.0</Ys>
   <Ys>1.0</Ys>
   <Ys>1.0</Ys>
   <Ys>1.0</Ys>
   <Ys>1.0</Ys>
   <Ys>1.0</Ys>
   <Ys>1.0</Ys>
   <Ys>1.0</Ys>
   <Ys>1.0</Ys>
   <Ys>1.0</Ys>
   <Ys>1.0</Ys>
   <Ys>1.0</Ys>
   <Ys>1.0</Ys>
   <Ys>1.0</Ys>
   <Ys>1.0</Ys>
   <Ys>1.0</Ys>
   <Ys>1.0</Ys>
   <Ys>1.0</Ys>
   <Ys>1.0</Ys>
   <Ys>1.0</Ys>
   <Ys>1.0</Ys>
   <Ys>1.0</Ys>
   <Ys>1.0</Ys>
   <Ys>1.0</Ys>
   <Ys>1.0</Ys>
   <Ys>1.0</Ys>
   <Ys>1.0</Ys>
   <Ys>1.0</Ys>
   <Ys>1.0</Ys>
   <Ys>1.0</Ys>
   <Ys>1.0</Ys>
   <Ys>1.0</Ys>
   <Ys>1.0</Ys>
   <Ys>1.0</Ys>
   <Ys>1.0</Ys>
   <Ys>1.0</Ys>
   <Ys>1.0</Ys>
   <Ys>1.0</Ys>
   <Ys>1.0</Ys>
   <Ys>1.0</Ys>
   <Ys>1.0</Ys>
   <Ys>1.0</Ys>
   <Ys>1.0</Ys>
   <Ys>1.0</Ys>
   <Ys>1.0</Ys>
   <Ys>1.0</Ys>
   <Ys>1.0</Ys>
   <Ys>1.0</Ys>
   <Ys>1.0</Ys>
   <Ys>1.0</Ys>
   <Ys>1.0</Ys>
   <Ys>1.0</Ys>
   <Ys>1.0</Ys>
   <Ys>1.0</Ys>
   <Ys>1.0</Ys>
   <Ys>1.0</Ys>
   <Ys>1.0</Ys>
   <Ys>1.0</Ys>
   <Ys>1.0</Ys>
   <Ys>1.0</Ys>
   <Ys>1.0</Ys>
   <Ys>1.0</Ys>
   <Ys>1.0</Ys>
   <Ys>1.0</Ys>
   <Ys>1.0</Ys>
   <Ys>1.0</Ys>
   <Ys>1.0</Ys>
   <Ys>1.0</Ys>
   <Ys>1.0</Ys>
   <Ys>1.0</Ys>
   <Ys>1.0</Ys>
   <Ys>1.0</Ys>
   <Ys>1.0</Ys>
   <Ys>1.0</Ys>
   <Ys>1.0</Ys>
   <Ys>1.0</Ys>
   <Ys>1.0</Ys>
   <Ys>1.0</Ys>
   <Ys>1.0</Ys>
   <Ys>1.0</Ys>
   <Ys>1.0</Ys>
   <Ys>1.0</Ys>
   <Ys>1.0</Ys>
   <Ys>1.0</Ys>
   <Ys>1.0</Ys>
   <Ys>1.0</Ys>
   <Ys>1.0</Ys>
   <Ys>1.0</Ys>
   <Ys>1.0</Ys>
   <Ys>1.0</Ys>
   <Ys>1.0</Ys>
   <Ys>1.0</Ys>
   <Ys>1.0</Ys>
   <Ys>1.0</Ys>
   <Ys>1.0</Ys>
   <Ys>1.0</Ys>
   <Ys>1.0</Ys>
   <Ys>1.0</Ys>
   <Ys>1.0</Ys>
   <Ys>1.0</Ys>
   <Ys>1.0</Ys>
   <Ys>1.0</Ys>
   <Ys>1.0</Ys>
   <Ys>1.0</Ys>
   <Ys>1.0</Ys>
   <Ys>1.0</Ys>
   <Ys>1.0</Ys>
   <Ys>1.0</Ys>
   <Ys>1.0</Ys>
   <Ys>1.0</Ys>
   <Ys>1.0</Ys>
   <Ys>1.0</Ys>
   <Ys>1.0</Ys>
   <Ys>1.0</Ys>
   <Ys>1.0</Ys>
   <Ys>1.0</Ys>
   <Ys>1.0</Ys>
   <Ys>1.0</Ys>
   <Ys>1.0</Ys>
   <Ys>1.0</Ys>
   <Ys>1.0</Ys>
   <Ys>1.0</Ys>
   <Ys>1.0</Ys>
   <Ys>1.0</Ys>
   <Ys>1.0</Ys>
   <Ys>1.0</Ys>
   <Ys>1.0</Ys>
   <Ys>1.0</Ys>
   <Ys>1.0</Ys>
   <Ys>1.0</Ys>
   <Ys>1.0</Ys>
   <Ys>1.0</Ys>
   <Ys>1.0</Ys>
   <Ys>1.0</Ys>
   <Ys>1.0</Ys>
   <Ys>1.0</Ys>
   <Ys>1.0</Ys>
   <Ys>1.0</Ys>
   <Ys>1.0</Ys>
   <Ys>1.0</Ys>
   <Ys>1.0</Ys>
   <Ys>1.0</Ys>
   <Ys>1.0</Ys>
   <Ys>1.0</Ys>
   <Ys>1.0</Ys>
   <Ys>1.0</Ys>
   <Ys>1.0</Ys>
   <Ys>1.0</Ys>
   <Ys>1.0</Ys>
   <Ys>1.0</Ys>
   <Ys>1.0</Ys>
   <Ys>1.0</Ys>
   <Ys>1.0</Ys>
   <Ys>1.0</Ys>
   <Ys>1.0</Ys>
   <Ys>1.0</Ys>
   <Ys>1.0</Ys>
   <Ys>1.0</Ys>
   <Ys>1.0</Ys>
   <Ys>1.0</Ys>
   <Ys>1.0</Ys>
   <Ys>1.0</Ys>
   <Ys>1.0</Ys>
   <Ys>1.0</Ys>
   <Ys>1.0</Ys>
   <Ys>1.0</Ys>
   <Ys>1.0</Ys>
   <Ys>1.0</Ys>
   <Ys>1.0</Ys>
   <Ys>1.0</Ys>
   <Ys>1.0</Ys>
   <Ys>1.0</Ys>
   <Ys>1.0</Ys>
   <Ys>1.0</Ys>
   <Ys>1.0</Ys>
   <Ys>1.0</Ys>
   <Ys>1.0</Ys>
   <Ys>1.0</Ys>
   <Ys>1.0</Ys>
   <Ys>1.0</Ys>
   <Ys>1.0</Ys>
   <Ys>1.0</Ys>
   <Ys>1.0</Ys>
   <Ys>1.0</Ys>
   <Ys>1.0</Ys>
   <Ys>1.0</Ys>
   <Ys>1.0</Ys>
   <Ys>1.0</Ys>
   <Ys>1.0</Ys>
   <Ys>1.0</Ys>
   <Ys>1.0</Ys>
   <Ys>1.0</Ys>
   <Ys>1.0</Ys>
   <Ys>1.0</Ys>
   <Ys>1.0</Ys>
   <Ys>1.0</Ys>
   <Ys>1.0</Ys>
   <Ys>1.0</Ys>
   <Ys>1.0</Ys>
   <Ys>1.0</Ys>
   <Ys>1.0</Ys>
   <Ys>1.0</Ys>
   <Ys>1.0</Ys>
   <Ys>1.0</Ys>
   <Ys>1.0</Ys>
   <Ys>1.0</Ys>
   <Ys>1.0</Ys>
   <Ys>1.0</Ys>
   <Ys>1.0</Ys>
   <Ys>1.0</Ys>
   <Ys>1.0</Ys>
   <Ys>1.0</Ys>
   <Ys>1.0</Ys>
   <Ys>1.0</Ys>
   <Ys>1.0</Ys>
   <Ys>1.0</Ys>
   <Ys>1.0</Ys>
   <Ys>1.0</Ys>
   <Ys>1.0</Ys>
   <Ys>1.0</Ys>
   <Ys>1.0</Ys>
   <Ys>1.0</Ys>
   <Ys>1.0</Ys>
   <Ys>1.0</Ys>
   <Ys>1.0</Ys>
   <Ys>1.0</Ys>
   <Ys>1.0</Ys>
   <Ys>1.0</Ys>
   <Ys>1.0</Ys>
   <Ys>1.0</Ys>
   <Ys>1.0</Ys>
   <Ys>1.0</Ys>
   <Ys>1.0</Ys>
   <Ys>1.0</Ys>
   <Ys>1.0</Ys>
   <Ys>1.0</Ys>
   <Ys>1.0</Ys>
   <Ys>1.0</Ys>
   <Ys>1.0</Ys>
   <Ys>1.0</Ys>
   <Ys>1.0</Ys>
   <Ys>1.0</Ys>
   <Ys>1.0</Ys>
   <Ys>1.0</Ys>
   <Ys>1.0</Ys>
   <Ys>1.0</Ys>
   <Ys>1.0</Ys>
   <Ys>1.0</Ys>
   <Ys>1.0</Ys>
   <Ys>1.0</Ys>
   <Ys>1.0</Ys>
   <Ys>1.0</Ys>
   <Ys>1.0</Ys>
   <Ys>1.0</Ys>
   <Ys>1.0</Ys>
   <Ys>1.0</Ys>
   <Ys>1.0</Ys>
   <Ys>1.0</Ys>
   <Ys>1.0</Ys>
   <Ys>1.0</Ys>
   <Ys>1.0</Ys>
   <Ys>1.0</Ys>
   <Ys>1.0</Ys>
   <Ys>1.0</Ys>
   <Ys>1.0</Ys>
   <Ys>1.0</Ys>
   <Ys>1.0</Ys>
   <Ys>1.0</Ys>
   <Ys>1.0</Ys>
   <Ys>1.0</Ys>
   <Ys>1.0</Ys>
   <Ys>1.0</Ys>
   <Ys>1.0</Ys>
   <Ys>1.0</Ys>
   <Ys>1.0</Ys>
   <Ys>1.0</Ys>
   <Ys>1.0</Ys>
   <Ys>1.0</Ys>
   <Ys>1.0</Ys>
   <Ys>1.0</Ys>
   <Ys>1.0</Ys>
   <Ys>1.0</Ys>
   <Ys>1.0</Ys>
   <Ys>1.0</Ys>
   <Ys>1.0</Ys>
   <Ys>1.0</Ys>
   <Ys>1.0</Ys>
   <Ys>1.0</Ys>
   <Ys>1.0</Ys>
   <Ys>1.0</Ys>
   <Ys>1.0</Ys>
   <Ys>1.0</Ys>
   <Ys>1.0</Ys>
   <Ys>1.0</Ys>
   <Ys>1.0</Ys>
   <Ys>1.0</Ys>
   <Ys>1.0</Ys>
   <Ys>1.0</Ys>
   <Ys>1.0</Ys>
   <Ys>1.0</Ys>
   <Ys>1.0</Ys>
   <Ys>1.0</Ys>
   <Ys>1.0</Ys>
   <Ys>1.0</Ys>
   <Ys>1.0</Ys>
   <Ys>1.0</Ys>
   <Ys>1.0</Ys>
   <Ys>1.0</Ys>
   <Ys>1.0</Ys>
   <Ys>1.0</Ys>
   <Ys>1.0</Ys>
   <Ys>1.0</Ys>
   <Ys>1.0</Ys>
   <Ys>1.0</Ys>
   <Ys>1.0</Ys>
   <Ys>1.0</Ys>
   <Ys>1.0</Ys>
   <Ys>1.0</Ys>
   <Ys>1.0</Ys>
   <Ys>1.0</Ys>
   <Ys>1.0</Ys>
   <Ys>1.0</Ys>
   <Ys>1.0</Ys>
   <Ys>1.0</Ys>
   <Ys>1.0</Ys>
   <Ys>1.0</Ys>
   <Ys>1.0</Ys>
   <Ys>1.0</Ys>
   <Ys>1.0</Ys>
   <Ys>1.0</Ys>
   <Ys>1.0</Ys>
   <Ys>1.0</Ys>
   <Ys>1.0</Ys>
   <Ys>1.0</Ys>
   <Ys>1.0</Ys>
   <Ys>1.0</Ys>
   <Ys>1.0</Ys>
   <Ys>1.0</Ys>
   <Ys>1.0</Ys>
   <Ys>1.0</Ys>
   <Ys>1.0</Ys>
   <Ys>1.0</Ys>
   <Ys>1.0</Ys>
   <Ys>1.0</Ys>
   <Ys>1.0</Ys>
   <Ys>1.0</Ys>
   <Ys>1.0</Ys>
   <Ys>1.0</Ys>
   <Ys>1.0</Ys>
   <Ys>1.0</Ys>
   <Ys>1.0</Ys>
   <Ys>1.0</Ys>
   <Ys>1.0</Ys>
   <Ys>1.0</Ys>
   <Ys>1.0</Ys>
   <Ys>1.0</Ys>
   <Ys>1.0</Ys>
   <Ys>1.0</Ys>
   <Ys>1.0</Ys>
   <Ys>1.0</Ys>
   <Ys>1.0</Ys>
   <Ys>1.0</Ys>
   <Ys>1.0</Ys>
   <Ys>1.0</Ys>
   <Ys>1.0</Ys>
   <Ys>1.0</Ys>
   <Ys>1.0</Ys>
   <Ys>1.0</Ys>
   <Ys>1.0</Ys>
   <Ys>1.0</Ys>
   <Ys>1.0</Ys>
   <Ys>1.0</Ys>
   <Ys>1.0</Ys>
   <Ys>1.0</Ys>
   <Ys>1.0</Ys>
   <Ys>1.0</Ys>
   <Ys>1.0</Ys>
   <Ys>1.0</Ys>
   <Ys>1.0</Ys>
   <Ys>1.0</Ys>
   <Ys>1.0</Ys>
   <Ys>1.0</Ys>
   <Ys>1.0</Ys>
   <Ys>1.0</Ys>
   <Ys>1.0</Ys>
   <Ys>1.0</Ys>
   <Ys>1.0</Ys>
   <Ys>1.0</Ys>
   <Ys>1.0</Ys>
   <Ys>1.0</Ys>
   <Ys>1.0</Ys>
   <Ys>1.0</Ys>
   <Ys>1.0</Ys>
   <Ys>1.0</Ys>
   <Ys>1.0</Ys>
   <Ys>1.0</Ys>
   <Ys>1.0</Ys>
   <Ys>1.0</Ys>
   <Ys>1.0</Ys>
   <Ys>1.0</Ys>
   <Ys>1.0</Ys>
   <Ys>1.0</Ys>
   <Ys>1.0</Ys>
   <Ys>1.0</Ys>
   <Ys>1.0</Ys>
   <Ys>1.0</Ys>
   <Ys>1.0</Ys>
   <Ys>1.0</Ys>
   <Ys>1.0</Ys>
   <Ys>1.0</Ys>
   <Ys>1.0</Ys>
   <Ys>1.0</Ys>
   <Ys>1.0</Ys>
   <Ys>1.0</Ys>
   <Ys>1.0</Ys>
   <Ys>1.0</Ys>
   <Ys>1.0</Ys>
   <Ys>1.0</Ys>
   <Ys>1.0</Ys>
   <Ys>1.0</Ys>
   <Ys>1.0</Ys>
   <Ys>1.0</Ys>
   <Ys>1.0</Ys>
   <Ys>1.0</Ys>
   <Ys>1.0</Ys>
   <Ys>1.0</Ys>
   <Ys>1.0</Ys>
   <Ys>1.0</Ys>
   <Ys>1.0</Ys>
   <Ys>1.0</Ys>
   <Ys>1.0</Ys>
   <Ys>1.0</Ys>
   <Ys>1.0</Ys>
   <Ys>1.0</Ys>
   <Ys>1.0</Ys>
   <Ys>1.0</Ys>
   <Ys>1.0</Ys>
   <Ys>1.0</Ys>
   <Ys>1.0</Ys>
   <Ys>1.0</Ys>
   <Ys>1.0</Ys>
   <Ys>1.0</Ys>
   <Ys>1.0</Ys>
   <Ys>1.0</Ys>
   <Ys>1.0</Ys>
   <Ys>1.0</Ys>
   <Ys>1.0</Ys>
   <Ys>1.0</Ys>
   <Ys>1.0</Ys>
   <Ys>1.0</Ys>
   <Ys>1.0</Ys>
   <Ys>1.0</Ys>
   <Ys>1.0</Ys>
   <Ys>1.0</Ys>
   <Ys>1.0</Ys>
   <Ys>1.0</Ys>
   <Ys>1.0</Ys>
   <Ys>1.0</Ys>
   <Ys>1.0</Ys>
   <Ys>1.0</Ys>
   <Ys>1.0</Ys>
   <Ys>1.0</Ys>
   <Ys>1.0</Ys>
   <Ys>1.0</Ys>
   <Ys>1.0</Ys>
   <Ys>1.0</Ys>
   <Ys>1.0</Ys>
   <Ys>1.0</Ys>
   <Ys>1.0</Ys>
   <Ys>1.0</Ys>
   <Ys>1.0</Ys>
   <Ys>1.0</Ys>
   <Ys>1.0</Ys>
   <Ys>1.0</Ys>
   <Ys>1.0</Ys>
   <Ys>1.0</Ys>
   <Ys>1.0</Ys>
   <Ys>1.0</Ys>
   <Ys>1.0</Ys>
   <Ys>1.0</Ys>
   <Ys>1.0</Ys>
   <Ys>1.0</Ys>
   <Ys>1.0</Ys>
   <Ys>1.0</Ys>
   <Ys>1.0</Ys>
   <Ys>1.0</Ys>
   <Ys>1.0</Ys>
   <Ys>1.0</Ys>
   <Ys>1.0</Ys>
   <Ys>1.0</Ys>
   <Ys>1.0</Ys>
   <Ys>1.0</Ys>
   <Ys>1.0</Ys>
   <Ys>1.0</Ys>
   <Ys>1.0</Ys>
   <Ys>1.0</Ys>
   <Ys>1.0</Ys>
   <Ys>1.0</Ys>
   <Ys>1.0</Ys>
   <Ys>1.0</Ys>
   <Ys>1.0</Ys>
   <Ys>1.0</Ys>
   <Ys>1.0</Ys>
   <Ys>1.0</Ys>
   <Ys>1.0</Ys>
   <Ys>1.0</Ys>
   <Ys>1.0</Ys>
   <Ys>1.0</Ys>
   <Ys>1.0</Ys>
   <Ys>1.0</Ys>
   <Ys>1.0</Ys>
   <Ys>1.0</Ys>
   <Ys>1.0</Ys>
   <Ys>1.0</Ys>
   <Ys>1.0</Ys>
   <Ys>1.0</Ys>
   <Ys>1.0</Ys>
   <Ys>1.0</Ys>
   <Ys>1.0</Ys>
   <Ys>1.0</Ys>
   <Ys>1.0</Ys>
   <Ys>1.0</Ys>
   <Ys>1.0</Ys>
   <Ys>1.0</Ys>
   <Ys>1.0</Ys>
   <Ys>1.0</Ys>
   <Ys>1.0</Ys>
   <Ys>1.0</Ys>
   <Ys>1.0</Ys>
   <Ys>1.0</Ys>
   <Ys>1.0</Ys>
   <Ys>1.0</Ys>
   <Ys>1.0</Ys>
   <Ys>1.0</Ys>
   <Ys>1.0</Ys>
   <Ys>1.0</Ys>
   <Ys>1.0</Ys>
   <Ys>1.0</Ys>
   <Ys>1.0</Ys>
   <Ys>1.0</Ys>
   <Ys>1.0</Ys>
   <Ys>1.0</Ys>
   <Ys>1.0</Ys>
   <Ys>1.0</Ys>
   <Ys>1.0</Ys>
   <Ys>1.0</Ys>
   <Ys>1.0</Ys>
   <Ys>1.0</Ys>
   <Ys>1.0</Ys>
   <Ys>1.0</Ys>
   <Ys>1.0</Ys>
   <Ys>1.0</Ys>
   <Ys>1.0</Ys>
   <Ys>1.0</Ys>
   <Ys>1.0</Ys>
   <Ys>1.0</Ys>
   <Ys>1.0</Ys>
   <Ys>1.0</Ys>
   <Ys>1.0</Ys>
   <Ys>1.0</Ys>
   <Ys>1.0</Ys>
   <Ys>1.0</Ys>
   <Ys>1.0</Ys>
   <Ys>1.0</Ys>
   <Ys>1.0</Ys>
   <Ys>1.0</Ys>
   <Ys>1.0</Ys>
   <Ys>1.0</Ys>
   <Ys>1.0</Ys>
   <Ys>1.0</Ys>
   <Ys>1.0</Ys>
   <Ys>1.0</Ys>
   <Ys>1.0</Ys>
   <Ys>1.0</Ys>
   <Ys>1.0</Ys>
   <Ys>1.0</Ys>
   <Ys>1.0</Ys>
   <Ys>1.0</Ys>
   <Ys>1.0</Ys>
   <Ys>1.0</Ys>
   <Ys>1.0</Ys>
   <Ys>1.0</Ys>
   <Ys>1.0</Ys>
   <Ys>1.0</Ys>
   <Ys>1.0</Ys>
   <Ys>1.0</Ys>
   <Ys>1.0</Ys>
   <Ys>1.0</Ys>
   <Ys>1.0</Ys>
   <Ys>1.0</Ys>
   <Ys>1.0</Ys>
   <Ys>1.0</Ys>
   <Ys>1.0</Ys>
   <Ys>1.0</Ys>
   <Ys>1.0</Ys>
   <Ys>1.0</Ys>
   <Ys>1.0</Ys>
   <Ys>1.0</Ys>
   <Ys>1.0</Ys>
   <Ys>1.0</Ys>
   <Ys>1.0</Ys>
   <Ys>1.0</Ys>
   <Ys>1.0</Ys>
   <Ys>1.0</Ys>
   <Ys>1.0</Ys>
   <Ys>1.0</Ys>
   <Ys>1.0</Ys>
   <Ys>1.0</Ys>
   <Ys>1.0</Ys>
   <Ys>1.0</Ys>
   <Ys>1.0</Ys>
   <Ys>1.0</Ys>
   <Ys>1.0</Ys>
   <Ys>1.0</Ys>
   <Ys>1.0</Ys>
   <Ys>1.0</Ys>
   <Ys>1.0</Ys>
   <Ys>1.0</Ys>
   <Ys>1.0</Ys>
   <Ys>1.0</Ys>
   <Ys>1.0</Ys>
   <Ys>1.0</Ys>
   <Ys>1.0</Ys>
   <Ys>1.0</Ys>
   <Ys>1.0</Ys>
   <Ys>1.0</Ys>
   <Ys>1.0</Ys>
   <Ys>1.0</Ys>
   <Ys>1.0</Ys>
   <Ys>1.0</Ys>
   <Ys>1.0</Ys>
   <Ys>1.0</Ys>
   <Ys>1.0</Ys>
   <Ys>1.0</Ys>
   <Ys>1.0</Ys>
   <Ys>1.0</Ys>
   <Ys>1.0</Ys>
   <Ys>1.0</Ys>
   <Ys>1.0</Ys>
   <Ys>1.0</Ys>
   <Ys>1.0</Ys>
   <Ys>1.0</Ys>
   <Ys>1.0</Ys>
   <Ys>1.0</Ys>
   <Ys>1.0</Ys>
   <Ys>1.0</Ys>
   <Ys>1.0</Ys>
   <Ys>1.0</Ys>
   <Ys>1.0</Ys>
   <Ys>1.0</Ys>
   <Ys>1.0</Ys>
   <Ys>1.0</Ys>
   <Ys>1.0</Ys>
   <Ys>1.0</Ys>
   <Ys>1.0</Ys>
   <Ys>1.0</Ys>
   <Ys>1.0</Ys>
   <Ys>1.0</Ys>
   <Ys>1.0</Ys>
   <Ys>1.0</Ys>
   <Ys>1.0</Ys>
   <Ys>1.0</Ys>
   <Ys>1.0</Ys>
   <Ys>1.0</Ys>
   <Ys>1.0</Ys>
   <Ys>1.0</Ys>
   <Ys>1.0</Ys>
   <Ys>1.0</Ys>
   <Ys>1.0</Ys>
   <Ys>1.0</Ys>
   <Ys>1.0</Ys>
   <Ys>1.0</Ys>
   <Ys>1.0</Ys>
   <Ys>1.0</Ys>
   <Ys>1.0</Ys>
   <Ys>1.0</Ys>
   <Ys>1.0</Ys>
   <Ys>1.0</Ys>
   <Ys>1.0</Ys>
   <Ys>1.0</Ys>
   <Ys>1.0</Ys>
   <Ys>1.0</Ys>
   <Ys>1.0</Ys>
   <Ys>1.0</Ys>
   <Ys>1.0</Ys>
   <Ys>1.0</Ys>
   <Ys>1.0</Ys>
   <Ys>1.0</Ys>
   <Ys>1.0</Ys>
   <Ys>1.0</Ys>
   <Ys>1.0</Ys>
   <Ys>1.0</Ys>
   <Ys>1.0</Ys>
   <Ys>1.0</Ys>
   <Ys>1.0</Ys>
   <Ys>1.0</Ys>
   <Ys>1.0</Ys>
   <Ys>1.0</Ys>
   <Ys>1.0</Ys>
   <Ys>1.0</Ys>
   <Ys>1.0</Ys>
   <Ys>1.0</Ys>
   <Ys>1.0</Ys>
   <Ys>1.0</Ys>
   <Ys>1.0</Ys>
   <Ys>1.0</Ys>
   <Ys>1.0</Ys>
   <Ys>1.0</Ys>
   <Ys>1.0</Ys>
   <Ys>1.0</Ys>
   <Ys>1.0</Ys>
   <Ys>1.0</Ys>
   <Ys>1.0</Ys>
   <Ys>1.0</Ys>
   <Ys>1.0</Ys>
   <Ys>1.0</Ys>
   <Ys>1.0</Ys>
   <Ys>1.0</Ys>
   <Ys>1.0</Ys>
   <Ys>1.0</Ys>
   <Ys>1.0</Ys>
   <Ys>1.0</Ys>
   <Ys>1.0</Ys>
   <Ys>1.0</Ys>
   <Ys>1.0</Ys>
   <Ys>1.0</Ys>
   <Ys>1.0</Ys>
   <Ys>1.0</Ys>
   <Ys>1.0</Ys>
   <Ys>1.0</Ys>
   <Ys>1.0</Ys>
   <Ys>1.0</Ys>
   <Ys>1.0</Ys>
   <Ys>1.0</Ys>
   <Ys>1.0</Ys>
   <Ys>1.0</Ys>
   <Ys>1.0</Ys>
   <Ys>1.0</Ys>
   <Ys>1.0</Ys>
   <Ys>1.0</Ys>
   <Ys>1.0</Ys>
   <Ys>1.0</Ys>
   <Ys>1.0</Ys>
   <Ys>1.0</Ys>
   <Ys>1.0</Ys>
   <Ys>1.0</Ys>
   <Ys>1.0</Ys>
   <Ys>1.0</Ys>
   <Ys>1.0</Ys>
   <Ys>1.0</Ys>
   <Ys>1.0</Ys>
   <Ys>1.0</Ys>
   <Ys>1.0</Ys>
   <Ys>1.0</Ys>
   <Ys>1.0</Ys>
   <Ys>1.0</Ys>
   <Ys>1.0</Ys>
   <Ys>1.0</Ys>
   <Ys>1.0</Ys>
   <Ys>1.0</Ys>
   <Ys>1.0</Ys>
   <Ys>1.0</Ys>
   <Ys>1.0</Ys>
   <Ys>1.0</Ys>
   <Ys>1.0</Ys>
   <Ys>1.0</Ys>
   <Ys>1.0</Ys>
   <Ys>1.0</Ys>
   <Ys>1.0</Ys>
   <Ys>1.0</Ys>
   <Ys>1.0</Ys>
   <Ys>1.0</Ys>
   <Ys>1.0</Ys>
   <Ys>1.0</Ys>
   <Ys>1.0</Ys>
   <Ys>1.0</Ys>
   <Ys>1.0</Ys>
   <Ys>1.0</Ys>
   <Ys>1.0</Ys>
   <Ys>1.0</Ys>
   <Ys>1.0</Ys>
   <Ys>1.0</Ys>
   <Ys>1.0</Ys>
   <Ys>1.0</Ys>
   <Ys>1.0</Ys>
   <Ys>1.0</Ys>
   <Ys>1.0</Ys>
   <Ys>1.0</Ys>
   <Ys>1.0</Ys>
   <Ys>1.0</Ys>
   <Ys>1.0</Ys>
   <Ys>1.0</Ys>
   <Ys>1.0</Ys>
   <Ys>1.0</Ys>
   <Ys>1.0</Ys>
   <Ys>1.0</Ys>
   <Ys>1.0</Ys>
   <Ys>1.0</Ys>
   <Ys>1.0</Ys>
   <Ys>1.0</Ys>
   <Ys>1.0</Ys>
   <Ys>1.0</Ys>
   <Ys>0.9999998979206369</Ys>
   <Ys>1.0</Ys>
   <Ys>1.0</Ys>
   <Ys>1.0</Ys>
   <Ys>1.0</Ys>
   <Ys>1.0</Ys>
   <Ys>1.0</Ys>
   <Ys>1.0</Ys>
   <Ys>1.0</Ys>
   <Ys>1.0</Ys>
   <Ys>1.0</Ys>
   <Ys>1.0</Ys>
   <Ys>1.0</Ys>
   <Ys>1.0</Ys>
   <Ys>1.0</Ys>
   <Ys>1.0</Ys>
   <Ys>1.0</Ys>
   <Ys>1.0</Ys>
   <Ys>1.0</Ys>
   <Ys>1.0</Ys>
   <Ys>1.0</Ys>
   <Ys>1.0</Ys>
   <Ys>1.0</Ys>
   <Ys>1.0</Ys>
   <Ys>1.0</Ys>
   <Ys>1.0</Ys>
   <Ys>1.0</Ys>
   <Ys>1.0</Ys>
   <Ys>1.0</Ys>
   <Ys>1.0</Ys>
   <Ys>1.0</Ys>
   <Ys>1.0</Ys>
   <Ys>1.0</Ys>
   <Ys>1.0</Ys>
   <Ys>1.0</Ys>
   <Ys>1.0</Ys>
   <Ys>1.0</Ys>
   <Ys>1.0</Ys>
   <Ys>1.0</Ys>
   <Ys>1.0</Ys>
   <Ys>1.0</Ys>
   <Ys>1.0</Ys>
   <Ys>1.0</Ys>
   <Ys>1.0</Ys>
   <Ys>1.0</Ys>
   <Ys>1.0</Ys>
   <Ys>1.0</Ys>
   <Ys>1.0</Ys>
   <Ys>1.0</Ys>
   <Ys>1.0</Ys>
   <Ys>1.0</Ys>
   <Ys>1.0</Ys>
   <Ys>1.0</Ys>
   <Ys>1.0</Ys>
   <Ys>1.0</Ys>
   <Ys>1.0</Ys>
   <Ys>1.0</Ys>
   <Ys>1.0</Ys>
   <Ys>1.0</Ys>
   <Ys>1.0</Ys>
   <Ys>1.0</Ys>
   <Ys>1.0</Ys>
   <Ys>1.0</Ys>
   <Ys>1.0</Ys>
   <Ys>1.0</Ys>
   <Ys>1.0</Ys>
   <Ys>1.0</Ys>
   <Ys>1.0</Ys>
   <Ys>1.0</Ys>
   <Ys>1.0</Ys>
   <Ys>1.0</Ys>
   <Ys>1.0</Ys>
   <Ys>1.0</Ys>
   <Ys>1.0</Ys>
   <Ys>1.0</Ys>
   <Ys>1.0</Ys>
   <Ys>1.0</Ys>
   <Ys>1.0</Ys>
   <Ys>1.0</Ys>
   <Ys>1.0207936305727948e-07</Ys>
   <Ys>1.0</Ys>
   <Ys>1.0</Ys>
   <Ys>1.0</Ys>
   <Ys>1.0</Ys>
   <Ys>1.0</Ys>
   <Ys>1.0</Ys>
   <Ys>1.0</Ys>
   <Ys>1.0</Ys>
   <Ys>1.0</Ys>
   <Ys>1.0</Ys>
   <Ys>1.0</Ys>
   <Ys>1.0</Ys>
   <Ys>1.0</Ys>
   <Ys>1.0</Ys>
   <Ys>1.0</Ys>
   <Ys>1.0</Ys>
   <Ys>1.0</Ys>
   <Ys>1.0</Ys>
   <Ys>1.0</Ys>
   <Ys>1.0</Ys>
   <Ys>1.0</Ys>
   <Ys>1.0</Ys>
   <Ys>1.0</Ys>
   <Ys>1.0</Ys>
   <Ys>1.0</Ys>
   <Ys>1.0</Ys>
   <Ys>1.0</Ys>
   <Ys>1.0</Ys>
   <Ys>1.0</Ys>
   <Ys>1.0</Ys>
   <Ys>1.0</Ys>
   <Ys>1.0</Ys>
   <Ys>1.0</Ys>
   <Ys>1.0</Ys>
   <Ys>1.0</Ys>
   <Ys>1.0</Ys>
   <Ys>1.0</Ys>
   <Ys>1.0</Ys>
   <Ys>1.0</Ys>
   <Ys>1.0</Ys>
   <Ys>1.0</Ys>
   <Ys>1.0</Ys>
   <Ys>1.0</Ys>
   <Ys>1.0</Ys>
   <Ys>1.0</Ys>
   <Ys>1.0</Ys>
   <Ys>1.0</Ys>
   <Ys>1.0</Ys>
   <Ys>1.0</Ys>
   <Ys>1.0</Ys>
   <Ys>1.0</Ys>
   <Ys>1.0</Ys>
   <Ys>1.0</Ys>
   <Ys>1.0</Ys>
   <Ys>1.0</Ys>
   <Ys>1.0</Ys>
   <Ys>1.0</Ys>
   <Ys>1.0</Ys>
   <Ys>1.0</Ys>
   <Ys>1.0</Ys>
   <Ys>1.0</Ys>
</root>